Workbook

Sheet product
A1: Basic Information | B1: Basic Information | C1: Basic Information | D1: Basic Information | E1: Basic Information | F1: Basic Information | G1: Basic Information | H1: Basic Information | I1: Basic Information | J1: Basic Information | K1: Basic Information | L1: Basic Information | M1: Basic Information | N1: Basic Information | O1: Product Attribute | P1: Product Attribute | Q1: Product Description | R1: Product Description | S1: Product Description | T1: Product Description | U1: Product Description | V1: Service | W1: Service | X1: Service | Y1: Service | Z1: Delivery | AA1: Delivery | AB1: Delivery | AC1: Delivery | AD1: Variant Attribute | AE1: Variant Attribute | AF1: Variant Attribute | AG1: *Variant Attribute | AH1: Variant Attribute | AI1: Variant Attribute | AJ1: Variant Attribute | AK1: Variant Attribute | AL1: Variant Attribute | AM1: Variant Attribute
A2: **Name (English) | B2: Name (Bengali) | C2: **Product Image 1 | D2: Product Image 2 | E2: Product Image 3 | F2: Product Image 4 | G2: Product Image 5 | H2: Product Image 6 | I2: Product Image 7 | J2: Product Image 8 | K2: VideoUrl | L2: **Brand | M2: **Unit | N2: Tags | O2: *Recommended Age | P2: *Main Materials | Q2: Highlights(English) | R2: Highlights(Bengali) | S2: Description (Bengali) | T2: Description (English) | U2: What's in the box | V2: Warranty Policy(English) | W2: Warranty Policy(Bangla) | X2: Warranty Type | Y2: Warranty Period | Z2: **Package Weight (kg) | AA2: **Package Length(cm) | AB2: *Package Width (cm) | AC2: *Package Height(cm) | AD2: *Color | AE2: **Seller SKU | AF2: **Parent Sku | AG2: *Variant Image | AH2: **Current Stock Qty | AI2: **Price(MRP) | AJ2: Special Price | AK2: Special Start Date | AL2: Special End Date | AM2: Free Items
A3: Hot Wheels Ferrari 5-Pack (Sealed) | B3: Hot Wheels Ferrari 5-Pack (সিলড) — ১:৬৪ ডাইকাস্ট মডেল কার সেট | C3: https://cdn.cartup.com/product/32443a23-ff9d-46a5-bb4c-a70a6d426705.webp | L3: No Brand | M3: PCS | N3: ferrari, 5-pack, sealed, multi-pack, gift | O3: 10 Years+ | P3: Alloy | Q3: Sealed 5-car Ferrari set; Officially licensed Ferrari liveries; Collectible sealed packaging | R3: সিলড ৫টি Ferrari গাড়ির সেট; অফিসিয়াল লাইসেন্সপ্রাপ্ত Ferrari লিভারি; সংগ্রাহকদের জন্য সিলড প্যাকেজিং | S3: সিলড ৫টি Ferrari গাড়ির সেট — Hot Wheels-এ Ferrari-র প্রত্যাবর্তন উপলক্ষে। সেটে আছে F40, SF90, 12Cilindri, Dino এবং 365 GTB/4। সিলড প্যাক একইসঙ্গে ডিসপ্লে পিস এবং সময়ের সঙ্গে দাম বাড়া কালেক্টিবল। স্কেল: 1:64 · প্রস্তুতকারক: Mattel · সিরিজ: Ferrari 5-Pack 2025 · মডেল নম্বর: JLN12 গঠন: Diecast metal body, plastic base, plastic wheels প্যাকেজিং: অরিজিনাল Hot Wheels ৫-প্যাক বক্সে সিলড প্রস্তুতকারকের বয়সসীমা: ৩ বছর ও তদূর্ধ্ব (Mattel অফিসিয়াল)। ১০০% আসল — DiecastBD কর্তৃক আমদানিকৃত ও হাতে যাচাইকৃত। | T3: Sealed 5-car Ferrari set marking Ferrari's return to Hot Wheels — F40, SF90, 12Cilindri, Dino and 365 GTB/4. Sealed packs are both a display piece and an appreciating collectible. Scale: 1:64 · Manufacturer: Mattel · Series: Ferrari 5-Pack 2025 · Model no: JLN12 Construction: Diecast metal body, plastic base, plastic wheels Packaging: sealed in the original Hot Wheels 5-pack box Manufacturer age grade: 3 years and up (Mattel official). 100% authentic — imported and hand-verified by DiecastBD. | U3: 1 x Hot Wheels Ferrari 5-Pack (Sealed), sealed in the original Hot Wheels 5-pack box (contains 5 x 1:64 diecast vehicles) | V3: No manufacturer or seller warranty is offered on collectible diecast models. Every piece is supplied factory-sealed in its original packaging, is 100% authentic, and is hand-inspected before dispatch. Report any transit damage with the unopened parcel on delivery. | W3: কালেক্টিবল ডাইকাস্ট মডেলের ক্ষেত্রে কোনো ম্যানুফ্যাকচারার বা সেলার ওয়ারেন্টি দেওয়া হয় না। প্রতিটি পিস অরিজিনাল প্যাকেজিংয়ে ফ্যাক্টরি-সিলড অবস্থায় সরবরাহ করা হয়, ১০০% আসল, এবং পাঠানোর আগে হাতে যাচাই করা হয়। ডেলিভারির সময় পার্সেল না খুলে ট্রানজিটে কোনো ক্ষতি হয়ে থাকলে সঙ্গে সঙ্গে জানান। | X3: No Warranty | Z3: 0.5 | AA3: 28 | AB3: 20 | AC3: 7 | AD3: Red | AE3: DCBD-HW5P-001 | AF3: DCBD-HW5P-001 | AG3: https://cdn.cartup.com/product/32443a23-ff9d-46a5-bb4c-a70a6d426705.webp | AH3: 4 | AI3: 3400 | AJ3: 3180 | AK3: 46231 | AL3: 46596.999
A4: Hot Wheels Formula 1 5-Pack (Sealed) | B4: Hot Wheels Formula 1 5-Pack (সিলড) — ১:৬৪ ডাইকাস্ট মডেল কার সেট | C4: https://cdn.cartup.com/product/0b3f8fe3-68b6-48a6-93fd-d62a27f081b6.webp | L4: No Brand | M4: PCS | N4: f1, formula 1, 5-pack, sealed, multi-pack, gift | O4: 10 Years+ | P4: Alloy | Q4: Sealed 5-car F1 grid set; 5 official F1 team liveries; Great gift for F1 fans | R4: সিলড ৫টি F1 গাড়ির গ্রিড সেট; ৫টি অফিসিয়াল F1 টিম লিভারি; F1 ভক্তদের জন্য দারুণ উপহার | S4: সিলড ৫টি F1 গ্রিড সেট: Oracle Red Bull, Mercedes-AMG Petronas, BWT Alpine, MoneyGram Haas এবং Atlassian Williams। যেকোনো F1 ভক্তের জন্য সবচেয়ে সহজ উপহার। স্কেল: 1:64 · প্রস্তুতকারক: Mattel · সিরিজ: Formula 1 5-Pack 2025 · মডেল নম্বর: JLN11 গঠন: Diecast metal body, plastic base, plastic wheels প্যাকেজিং: অরিজিনাল Hot Wheels ৫-প্যাক বক্সে সিলড প্রস্তুতকারকের বয়সসীমা: ৩ বছর ও তদূর্ধ্ব (Mattel অফিসিয়াল)। ১০০% আসল — DiecastBD কর্তৃক আমদানিকৃত ও হাতে যাচাইকৃত। | T4: Sealed 5-car F1 grid set: Oracle Red Bull, Mercedes-AMG Petronas, BWT Alpine, MoneyGram Haas and Atlassian Williams. The easiest gift-in for any F1 fan. Scale: 1:64 · Manufacturer: Mattel · Series: Formula 1 5-Pack 2025 · Model no: JLN11 Construction: Diecast metal body, plastic base, plastic wheels Packaging: sealed in the original Hot Wheels 5-pack box Manufacturer age grade: 3 years and up (Mattel official). 100% authentic — imported and hand-verified by DiecastBD. | U4: 1 x Hot Wheels Formula 1 5-Pack (Sealed), sealed in the original Hot Wheels 5-pack box (contains 5 x 1:64 diecast vehicles) | V4: No manufacturer or seller warranty is offered on collectible diecast models. Every piece is supplied factory-sealed in its original packaging, is 100% authentic, and is hand-inspected before dispatch. Report any transit damage with the unopened parcel on delivery. | W4: কালেক্টিবল ডাইকাস্ট মডেলের ক্ষেত্রে কোনো ম্যানুফ্যাকচারার বা সেলার ওয়ারেন্টি দেওয়া হয় না। প্রতিটি পিস অরিজিনাল প্যাকেজিংয়ে ফ্যাক্টরি-সিলড অবস্থায় সরবরাহ করা হয়, ১০০% আসল, এবং পাঠানোর আগে হাতে যাচাই করা হয়। ডেলিভারির সময় পার্সেল না খুলে ট্রানজিটে কোনো ক্ষতি হয়ে থাকলে সঙ্গে সঙ্গে জানান। | X4: No Warranty | Z4: 0.5 | AA4: 28 | AB4: 20 | AC4: 7 | AD4: Multicolor | AE4: DCBD-HW5P-002 | AF4: DCBD-HW5P-002 | AG4: https://cdn.cartup.com/product/0b3f8fe3-68b6-48a6-93fd-d62a27f081b6.webp | AH4: 2 | AI4: 2550 | AJ4: 2380 | AK4: 46231 | AL4: 46596.999
A5: Hot Wheels Car Culture — Ferrari 250 GTO (Vintage Racing Club) | B5: Hot Wheels Car Culture — Ferrari 250 GTO ১:৬৪ ডাইকাস্ট মডেল কার (Vintage Racing Club) | C5: https://cdn.cartup.com/product/2f33e0a9-85a1-41cf-9c96-530c9264408e.webp | L5: No Brand | M5: PCS | N5: car culture, ferrari, 250 gto, vintage racing, classic | O5: 10 Years+ | P5: Alloy | Q5: Car Culture premium series; Metal body & metal base; Real Riders rubber tyres | R5: Car Culture প্রিমিয়াম সিরিজ; মেটাল বডি ও মেটাল বেস; Real Riders রাবার টায়ার | S5: Ferrari 250 GTO — পৃথিবীর সবচেয়ে দামি গাড়ি (একটি আসল গাড়ি ৭ কোটি ডলারে বিক্রি হয়েছে)। Car Culture প্রিমিয়াম বিল্ড, মেটাল বেস ও Real Riders রাবার টায়ার সহ। স্কেল: 1:64 · প্রস্তুতকারক: Mattel · সিরিজ: Car Culture — Vintage Racing Club · মডেল নম্বর: FPY86 গঠন: Diecast metal body, metal base, Real Riders rubber tyres প্যাকেজিং: অরিজিনাল Hot Wheels প্রিমিয়াম ব্লিস্টার কার্ডে সিলড প্রস্তুতকারকের বয়সসীমা: ৩ বছর ও তদূর্ধ্ব (Mattel অফিসিয়াল)। ১০০% আসল — DiecastBD কর্তৃক আমদানিকৃত ও হাতে যাচাইকৃত। | T5: The Ferrari 250 GTO — the most valuable car on earth (a real one sold for $70M). Car Culture premium with metal base and Real Riders. Scale: 1:64 · Manufacturer: Mattel · Series: Car Culture — Vintage Racing Club · Model no: FPY86 Construction: Diecast metal body, metal base, Real Riders rubber tyres Packaging: sealed on the original Hot Wheels premium blister card Manufacturer age grade: 3 years and up (Mattel official). 100% authentic — imported and hand-verified by DiecastBD. | U5: 1 x Hot Wheels Car Culture — Ferrari 250 GTO (Vintage Racing Club), sealed on the original Hot Wheels premium blister card | V5: No manufacturer or seller warranty is offered on collectible diecast models. Every piece is supplied factory-sealed in its original packaging, is 100% authentic, and is hand-inspected before dispatch. Report any transit damage with the unopened parcel on delivery. | W5: কালেক্টিবল ডাইকাস্ট মডেলের ক্ষেত্রে কোনো ম্যানুফ্যাকচারার বা সেলার ওয়ারেন্টি দেওয়া হয় না। প্রতিটি পিস অরিজিনাল প্যাকেজিংয়ে ফ্যাক্টরি-সিলড অবস্থায় সরবরাহ করা হয়, ১০০% আসল, এবং পাঠানোর আগে হাতে যাচাই করা হয়। ডেলিভারির সময় পার্সেল না খুলে ট্রানজিটে কোনো ক্ষতি হয়ে থাকলে সঙ্গে সঙ্গে জানান। | X5: No Warranty | Z5: 0.2 | AA5: 18 | AB5: 15 | AC5: 6 | AD5: White | AE5: DCBD-HWCC-001 | AF5: DCBD-HWCC-001 | AG5: https://cdn.cartup.com/product/2f33e0a9-85a1-41cf-9c96-530c9264408e.webp | AH5: 1 | AI5: 2280 | AJ5: 2130 | AK5: 46231 | AL5: 46596.999
A6: Hot Wheels Car Culture — Porsche 917K (Vintage Racing Club) | B6: Hot Wheels Car Culture — Porsche 917K ১:৬৪ ডাইকাস্ট মডেল কার (Vintage Racing Club) | C6: https://cdn.cartup.com/product/34a8c7fa-eef0-41c4-802d-112ed9316efd.webp | L6: No Brand | M6: PCS | N6: car culture, porsche, 917k, le mans, vintage racing | O6: 10 Years+ | P6: Alloy | Q6: Car Culture premium series; Metal body & metal base; Real Riders rubber tyres | R6: Car Culture প্রিমিয়াম সিরিজ; মেটাল বডি ও মেটাল বেস; Real Riders রাবার টায়ার | S6: Le Mans-জয়ী Porsche 917K, তার আইকনিক #20 রেসিং লিভারিতে। প্রিমিয়াম Car Culture বিল্ড — মেটাল বডি, মেটাল বেস ও Real Riders রাবার টায়ার। স্কেল: 1:64 · প্রস্তুতকারক: Mattel · সিরিজ: Car Culture — Vintage Racing Club · মডেল নম্বর: FPY86 গঠন: Diecast metal body, metal base, Real Riders rubber tyres প্যাকেজিং: অরিজিনাল Hot Wheels প্রিমিয়াম ব্লিস্টার কার্ডে সিলড প্রস্তুতকারকের বয়সসীমা: ৩ বছর ও তদূর্ধ্ব (Mattel অফিসিয়াল)। ১০০% আসল — DiecastBD কর্তৃক আমদানিকৃত ও হাতে যাচাইকৃত। | T6: The Le Mans-winning Porsche 917K in its iconic #20 racing livery. Premium Car Culture build — metal/metal, Real Riders. Scale: 1:64 · Manufacturer: Mattel · Series: Car Culture — Vintage Racing Club · Model no: FPY86 Construction: Diecast metal body, metal base, Real Riders rubber tyres Packaging: sealed on the original Hot Wheels premium blister card Manufacturer age grade: 3 years and up (Mattel official). 100% authentic — imported and hand-verified by DiecastBD. | U6: 1 x Hot Wheels Car Culture — Porsche 917K (Vintage Racing Club), sealed on the original Hot Wheels premium blister card | V6: No manufacturer or seller warranty is offered on collectible diecast models. Every piece is supplied factory-sealed in its original packaging, is 100% authentic, and is hand-inspected before dispatch. Report any transit damage with the unopened parcel on delivery. | W6: কালেক্টিবল ডাইকাস্ট মডেলের ক্ষেত্রে কোনো ম্যানুফ্যাকচারার বা সেলার ওয়ারেন্টি দেওয়া হয় না। প্রতিটি পিস অরিজিনাল প্যাকেজিংয়ে ফ্যাক্টরি-সিলড অবস্থায় সরবরাহ করা হয়, ১০০% আসল, এবং পাঠানোর আগে হাতে যাচাই করা হয়। ডেলিভারির সময় পার্সেল না খুলে ট্রানজিটে কোনো ক্ষতি হয়ে থাকলে সঙ্গে সঙ্গে জানান। | X6: No Warranty | Z6: 0.2 | AA6: 18 | AB6: 15 | AC6: 6 | AD6: White | AE6: DCBD-HWCC-002 | AF6: DCBD-HWCC-002 | AG6: https://cdn.cartup.com/product/34a8c7fa-eef0-41c4-802d-112ed9316efd.webp | AH6: 1 | AI6: 1860 | AJ6: 1740 | AK6: 46231 | AL6: 46596.999
A7: Hot Wheels Boulevard No.150 — Nissan Skyline GT-R R32 Pandem (HKS) | B7: Hot Wheels Boulevard No.150 — Nissan Skyline GT-R R32 Pandem (HKS) ১:৬৪ ডাইকাস্ট মডেল কার | C7: https://cdn.cartup.com/product/7c7d582e-685d-4fec-b5d9-cb277eea72e6.webp | L7: No Brand | M7: PCS | N7: jdm, nissan, skyline, r32, gt-r, pandem, hks, boulevard, godzilla | O7: 10 Years+ | P7: Alloy | Q7: Boulevard premium series; Pandem widebody kit; HKS racing livery; Real Riders rubber tyres | R7: Boulevard প্রিমিয়াম সিরিজ; Pandem ওয়াইডবডি কিট; HKS রেসিং লিভারি; Real Riders রাবার টায়ার | S7: Godzilla — সম্পূর্ণ Pandem ওয়াইডবডি এবং কিংবদন্তি HKS রঙে। Boulevard প্রিমিয়াম — মেটাল বেস, Real Riders রাবার টায়ার। এ বছরের সবচেয়ে চাহিদাসম্পন্ন R32 কাস্টিংগুলোর একটি। স্কেল: 1:64 · প্রস্তুতকারক: Mattel · সিরিজ: Boulevard #150 · মডেল নম্বর: GJT68 গঠন: Diecast metal body, metal base, Real Riders rubber tyres প্যাকেজিং: অরিজিনাল Hot Wheels প্রিমিয়াম ব্লিস্টার কার্ডে সিলড প্রস্তুতকারকের বয়সসীমা: ৩ বছর ও তদূর্ধ্ব (Mattel অফিসিয়াল)। ১০০% আসল — DiecastBD কর্তৃক আমদানিকৃত ও হাতে যাচাইকৃত। | T7: Godzilla in full Pandem widebody and legendary HKS colours. Boulevard premium — metal base, Real Riders. One of the most wanted R32 castings of the year. Scale: 1:64 · Manufacturer: Mattel · Series: Boulevard #150 · Model no: GJT68 Construction: Diecast metal body, metal base, Real Riders rubber tyres Packaging: sealed on the original Hot Wheels premium blister card Manufacturer age grade: 3 years and up (Mattel official). 100% authentic — imported and hand-verified by DiecastBD. | U7: 1 x Hot Wheels Boulevard No.150 — Nissan Skyline GT-R R32 Pandem (HKS), sealed on the original Hot Wheels premium blister card | V7: No manufacturer or seller warranty is offered on collectible diecast models. Every piece is supplied factory-sealed in its original packaging, is 100% authentic, and is hand-inspected before dispatch. Report any transit damage with the unopened parcel on delivery. | W7: কালেক্টিবল ডাইকাস্ট মডেলের ক্ষেত্রে কোনো ম্যানুফ্যাকচারার বা সেলার ওয়ারেন্টি দেওয়া হয় না। প্রতিটি পিস অরিজিনাল প্যাকেজিংয়ে ফ্যাক্টরি-সিলড অবস্থায় সরবরাহ করা হয়, ১০০% আসল, এবং পাঠানোর আগে হাতে যাচাই করা হয়। ডেলিভারির সময় পার্সেল না খুলে ট্রানজিটে কোনো ক্ষতি হয়ে থাকলে সঙ্গে সঙ্গে জানান। | X7: No Warranty | Z7: 0.2 | AA7: 18 | AB7: 15 | AC7: 6 | AD7: Blue | AE7: DCBD-HWCC-003 | AF7: DCBD-HWCC-003 | AG7: https://cdn.cartup.com/product/7c7d582e-685d-4fec-b5d9-cb277eea72e6.webp | AH7: 2 | AI7: 1980 | AJ7: 1850 | AK7: 46231 | AL7: 46596.999
A8: Hot Wheels Car Culture — BMW M3 E46 (Power Trip) | B8: Hot Wheels Car Culture — BMW M3 E46 ১:৬৪ ডাইকাস্ট মডেল কার (Power Trip) | C8: https://cdn.cartup.com/product/8f1fb6dd-75ff-4e14-9de3-90d1cfcdd56d.webp | L8: No Brand | M8: PCS | N8: car culture, bmw, m3, e46, power trip | O8: 10 Years+ | P8: Alloy | Q8: Car Culture premium series; Metal body & metal base; Real Riders rubber tyres | R8: Car Culture প্রিমিয়াম সিরিজ; মেটাল বডি ও মেটাল বেস; Real Riders রাবার টায়ার | S8: E46 M3 — গাড়িপ্রেমীদের BMW — গাঢ় সবুজ রঙে, প্রিমিয়াম Power Trip কার্ডে। মেটাল বডি ও মেটাল বেস, সঙ্গে Real Riders রাবার টায়ার। স্কেল: 1:64 · প্রস্তুতকারক: Mattel · সিরিজ: Car Culture — Power Trip · মডেল নম্বর: FPY86 গঠন: Diecast metal body, metal base, Real Riders rubber tyres প্যাকেজিং: অরিজিনাল Hot Wheels প্রিমিয়াম ব্লিস্টার কার্ডে সিলড প্রস্তুতকারকের বয়সসীমা: ৩ বছর ও তদূর্ধ্ব (Mattel অফিসিয়াল)। ১০০% আসল — DiecastBD কর্তৃক আমদানিকৃত ও হাতে যাচাইকৃত। | T8: The E46 M3 — the enthusiast's BMW — in deep green on a premium Power Trip card. Metal/metal with Real Riders. Scale: 1:64 · Manufacturer: Mattel · Series: Car Culture — Power Trip · Model no: FPY86 Construction: Diecast metal body, metal base, Real Riders rubber tyres Packaging: sealed on the original Hot Wheels premium blister card Manufacturer age grade: 3 years and up (Mattel official). 100% authentic — imported and hand-verified by DiecastBD. | U8: 1 x Hot Wheels Car Culture — BMW M3 E46 (Power Trip), sealed on the original Hot Wheels premium blister card | V8: No manufacturer or seller warranty is offered on collectible diecast models. Every piece is supplied factory-sealed in its original packaging, is 100% authentic, and is hand-inspected before dispatch. Report any transit damage with the unopened parcel on delivery. | W8: কালেক্টিবল ডাইকাস্ট মডেলের ক্ষেত্রে কোনো ম্যানুফ্যাকচারার বা সেলার ওয়ারেন্টি দেওয়া হয় না। প্রতিটি পিস অরিজিনাল প্যাকেজিংয়ে ফ্যাক্টরি-সিলড অবস্থায় সরবরাহ করা হয়, ১০০% আসল, এবং পাঠানোর আগে হাতে যাচাই করা হয়। ডেলিভারির সময় পার্সেল না খুলে ট্রানজিটে কোনো ক্ষতি হয়ে থাকলে সঙ্গে সঙ্গে জানান। | X8: No Warranty | Z8: 0.2 | AA8: 18 | AB8: 15 | AC8: 6 | AD8: Dark Green | AE8: DCBD-HWCC-004 | AF8: DCBD-HWCC-004 | AG8: https://cdn.cartup.com/product/8f1fb6dd-75ff-4e14-9de3-90d1cfcdd56d.webp | AH8: 1 | AI8: 2070 | AJ8: 1930 | AK8: 46231 | AL8: 46596.999
A9: Hot Wheels Car Culture — Nissan Skyline GT-R R32 Pandem, Yellow (Ronin Run II) | B9: Hot Wheels Car Culture — Nissan Skyline GT-R R32 Pandem হলুদ ১:৬৪ ডাইকাস্ট মডেল কার (Ronin Run II) | C9: https://cdn.cartup.com/product/a47f07ca-58c7-4173-8a36-14f9b3a2a61b.webp | L9: No Brand | M9: PCS | N9: jdm, nissan, skyline, r32, gt-r, pandem, ronin run, godzilla | O9: 10 Years+ | P9: Alloy | Q9: Car Culture premium series; Pandem widebody kit; Real Riders rubber tyres | R9: Car Culture প্রিমিয়াম সিরিজ; Pandem ওয়াইডবডি কিট; Real Riders রাবার টায়ার | S9: Ronin Run II সিরিজের Pandem-কিট R32 GT-R, উজ্জ্বল হলুদ রঙে। প্রিমিয়াম মেটাল বেস এবং Real Riders রাবার টায়ার। স্কেল: 1:64 · প্রস্তুতকারক: Mattel · সিরিজ: Car Culture — Ronin Run II · মডেল নম্বর: FPY86 গঠন: Diecast metal body, metal base, Real Riders rubber tyres প্যাকেজিং: অরিজিনাল Hot Wheels প্রিমিয়াম ব্লিস্টার কার্ডে সিলড প্রস্তুতকারকের বয়সসীমা: ৩ বছর ও তদূর্ধ্ব (Mattel অফিসিয়াল)। ১০০% আসল — DiecastBD কর্তৃক আমদানিকৃত ও হাতে যাচাইকৃত। | T9: Pandem-kitted R32 GT-R in bold yellow from the Ronin Run II series. Premium metal base and Real Riders. Scale: 1:64 · Manufacturer: Mattel · Series: Car Culture — Ronin Run II · Model no: FPY86 Construction: Diecast metal body, metal base, Real Riders rubber tyres Packaging: sealed on the original Hot Wheels premium blister card Manufacturer age grade: 3 years and up (Mattel official). 100% authentic — imported and hand-verified by DiecastBD. | U9: 1 x Hot Wheels Car Culture — Nissan Skyline GT-R R32 Pandem, Yellow (Ronin Run II), sealed on the original Hot Wheels premium blister card | V9: No manufacturer or seller warranty is offered on collectible diecast models. Every piece is supplied factory-sealed in its original packaging, is 100% authentic, and is hand-inspected before dispatch. Report any transit damage with the unopened parcel on delivery. | W9: কালেক্টিবল ডাইকাস্ট মডেলের ক্ষেত্রে কোনো ম্যানুফ্যাকচারার বা সেলার ওয়ারেন্টি দেওয়া হয় না। প্রতিটি পিস অরিজিনাল প্যাকেজিংয়ে ফ্যাক্টরি-সিলড অবস্থায় সরবরাহ করা হয়, ১০০% আসল, এবং পাঠানোর আগে হাতে যাচাই করা হয়। ডেলিভারির সময় পার্সেল না খুলে ট্রানজিটে কোনো ক্ষতি হয়ে থাকলে সঙ্গে সঙ্গে জানান। | X9: No Warranty | Z9: 0.2 | AA9: 18 | AB9: 15 | AC9: 6 | AD9: Yellow | AE9: DCBD-HWCC-005 | AF9: DCBD-HWCC-005 | AG9: https://cdn.cartup.com/product/a47f07ca-58c7-4173-8a36-14f9b3a2a61b.webp | AH9: 1 | AI9: 1670 | AJ9: 1560 | AK9: 46231 | AL9: 46596.999
A10: Hot Wheels Car Culture — Mad Mike Mazda RX-3 Wagon + Trailer (Ronin Run II) | B10: Hot Wheels Car Culture — Mad Mike Mazda RX-3 Wagon + Trailer ১:৬৪ ডাইকাস্ট মডেল কার (Ronin Run II) | C10: https://cdn.cartup.com/product/bc3d35a6-d010-425e-a8e6-e656fa566d50.webp | L10: No Brand | M10: PCS | N10: jdm, mazda, rx-3, mad mike, rotary, ronin run, bd exclusive | O10: 10 Years+ | P10: Alloy | Q10: Car Culture premium series; Includes matching trailer; Toyo Tires livery; Real Riders rubber tyres | R10: Car Culture প্রিমিয়াম সিরিজ; সঙ্গে ম্যাচিং ট্রেইলার; Toyo Tires লিভারি; Real Riders রাবার টায়ার | S10: Mad Mike-এর রোটারি Mazda RX-3 ওয়াগন, সঙ্গে ম্যাচিং ট্রেইলার পিস — একটি প্রিমিয়াম কার্ডে দুটি মডেল। স্কেল: 1:64 · প্রস্তুতকারক: Mattel · সিরিজ: Car Culture — Ronin Run II · মডেল নম্বর: FPY86 গঠন: Diecast metal body, metal base, Real Riders rubber tyres প্যাকেজিং: অরিজিনাল Hot Wheels প্রিমিয়াম ব্লিস্টার কার্ডে সিলড প্রস্তুতকারকের বয়সসীমা: ৩ বছর ও তদূর্ধ্ব (Mattel অফিসিয়াল)। ১০০% আসল — DiecastBD কর্তৃক আমদানিকৃত ও হাতে যাচাইকৃত। | T10: Mad Mike's rotary Mazda RX-3 wagon complete with a matching trailer piece — two models on one premium card. Scale: 1:64 · Manufacturer: Mattel · Series: Car Culture — Ronin Run II · Model no: FPY86 Construction: Diecast metal body, metal base, Real Riders rubber tyres Packaging: sealed on the original Hot Wheels premium blister card Manufacturer age grade: 3 years and up (Mattel official). 100% authentic — imported and hand-verified by DiecastBD. | U10: 1 x Hot Wheels Car Culture — Mad Mike Mazda RX-3 Wagon + Trailer (Ronin Run II), sealed on the original Hot Wheels premium blister card | V10: No manufacturer or seller warranty is offered on collectible diecast models. Every piece is supplied factory-sealed in its original packaging, is 100% authentic, and is hand-inspected before dispatch. Report any transit damage with the unopened parcel on delivery. | W10: কালেক্টিবল ডাইকাস্ট মডেলের ক্ষেত্রে কোনো ম্যানুফ্যাকচারার বা সেলার ওয়ারেন্টি দেওয়া হয় না। প্রতিটি পিস অরিজিনাল প্যাকেজিংয়ে ফ্যাক্টরি-সিলড অবস্থায় সরবরাহ করা হয়, ১০০% আসল, এবং পাঠানোর আগে হাতে যাচাই করা হয়। ডেলিভারির সময় পার্সেল না খুলে ট্রানজিটে কোনো ক্ষতি হয়ে থাকলে সঙ্গে সঙ্গে জানান। | X10: No Warranty | Z10: 0.2 | AA10: 18 | AB10: 15 | AC10: 6 | AD10: Blue | AE10: DCBD-HWCC-006 | AF10: DCBD-HWCC-006 | AG10: https://cdn.cartup.com/product/bc3d35a6-d010-425e-a8e6-e656fa566d50.webp | AH10: 2 | AI10: 1950 | AJ10: 1820 | AK10: 46231 | AL10: 46596.999
A11: Hot Wheels Car Culture — Ferrari Testarossa (Modern Classics, 10th Anniversary) | B11: Hot Wheels Car Culture — Ferrari Testarossa ১:৬৪ ডাইকাস্ট মডেল কার (Modern Classics, 10th Anniversary) | C11: https://cdn.cartup.com/product/fc485c81-2772-43d6-8958-17eaf7727768.webp | L11: No Brand | M11: PCS | N11: car culture, ferrari, testarossa, modern classics, 80s | O11: 10 Years+ | P11: Alloy | Q11: Car Culture 10th Anniversary; Metal body & metal base; Real Riders rubber tyres | R11: Car Culture ১০ম বার্ষিকী সংস্করণ; মেটাল বডি ও মেটাল বেস; Real Riders রাবার টায়ার | S11: আশির দশকের পোস্টার কার — Ferrari Testarossa, তার চিরচেনা লাল রঙে, Car Culture-এর ১০ম বার্ষিকী কার্ডে। মেটাল বডি ও মেটাল বেস, Real Riders রাবার টায়ার। স্কেল: 1:64 · প্রস্তুতকারক: Mattel · সিরিজ: Car Culture — Modern Classics (10th Anniversary) · মডেল নম্বর: FPY86 গঠন: Diecast metal body, metal base, Real Riders rubber tyres প্যাকেজিং: অরিজিনাল Hot Wheels প্রিমিয়াম ব্লিস্টার কার্ডে সিলড প্রস্তুতকারকের বয়সসীমা: ৩ বছর ও তদূর্ধ্ব (Mattel অফিসিয়াল)। ১০০% আসল — DiecastBD কর্তৃক আমদানিকৃত ও হাতে যাচাইকৃত। | T11: The 80s poster car — Ferrari Testarossa in signature red on the Car Culture 10th-anniversary card. Metal/metal, Real Riders. Scale: 1:64 · Manufacturer: Mattel · Series: Car Culture — Modern Classics (10th Anniversary) · Model no: FPY86 Construction: Diecast metal body, metal base, Real Riders rubber tyres Packaging: sealed on the original Hot Wheels premium blister card Manufacturer age grade: 3 years and up (Mattel official). 100% authentic — imported and hand-verified by DiecastBD. | U11: 1 x Hot Wheels Car Culture — Ferrari Testarossa (Modern Classics, 10th Anniversary), sealed on the original Hot Wheels premium blister card | V11: No manufacturer or seller warranty is offered on collectible diecast models. Every piece is supplied factory-sealed in its original packaging, is 100% authentic, and is hand-inspected before dispatch. Report any transit damage with the unopened parcel on delivery. | W11: কালেক্টিবল ডাইকাস্ট মডেলের ক্ষেত্রে কোনো ম্যানুফ্যাকচারার বা সেলার ওয়ারেন্টি দেওয়া হয় না। প্রতিটি পিস অরিজিনাল প্যাকেজিংয়ে ফ্যাক্টরি-সিলড অবস্থায় সরবরাহ করা হয়, ১০০% আসল, এবং পাঠানোর আগে হাতে যাচাই করা হয়। ডেলিভারির সময় পার্সেল না খুলে ট্রানজিটে কোনো ক্ষতি হয়ে থাকলে সঙ্গে সঙ্গে জানান। | X11: No Warranty | Z11: 0.2 | AA11: 18 | AB11: 15 | AC11: 6 | AD11: Red | AE11: DCBD-HWCC-007 | AF11: DCBD-HWCC-007 | AG11: https://cdn.cartup.com/product/fc485c81-2772-43d6-8958-17eaf7727768.webp | AH11: 2 | AI11: 2300 | AJ11: 2150 | AK11: 46231 | AL11: 46596.999
A12: Hot Wheels Car Culture — Nissan Skyline 2000GT-R LBWK (Japan Historics) | B12: Hot Wheels Car Culture — Nissan Skyline 2000GT-R LBWK ১:৬৪ ডাইকাস্ট মডেল কার (Japan Historics) | C12: https://cdn.cartup.com/product/480da80f-7c29-4561-a908-4581f0f8841b.webp | L12: No Brand | M12: PCS | N12: jdm, nissan, skyline, hakosuka, lbwk, liberty walk, gold label | O12: 10 Years+ | P12: Alloy | Q12: Gold Label premium series; Liberty Walk widebody; Real Riders rubber tyres | R12: Gold Label প্রিমিয়াম সিরিজ; Liberty Walk ওয়াইডবডি; Real Riders রাবার টায়ার | S12: Hakosuka Skyline 2000GT-R, Liberty Walk ওয়াইডবডি সহ — পুরোনো দিনের JDM-এর সঙ্গে আধুনিক টিউনার কালচারের মিলন। প্রিমিয়াম গোল্ড-লেবেল বিল্ড। স্কেল: 1:64 · প্রস্তুতকারক: Mattel · সিরিজ: Car Culture — Japan Historics 5 (Gold Label) · মডেল নম্বর: FPY86 গঠন: Diecast metal body, metal base, Real Riders rubber tyres প্যাকেজিং: অরিজিনাল Hot Wheels প্রিমিয়াম ব্লিস্টার কার্ডে সিলড প্রস্তুতকারকের বয়সসীমা: ৩ বছর ও তদূর্ধ্ব (Mattel অফিসিয়াল)। ১০০% আসল — DiecastBD কর্তৃক আমদানিকৃত ও হাতে যাচাইকৃত। | T12: Hakosuka Skyline 2000GT-R wearing a Liberty Walk widebody — vintage JDM meets modern tuner culture. Premium gold-label build. Scale: 1:64 · Manufacturer: Mattel · Series: Car Culture — Japan Historics 5 (Gold Label) · Model no: FPY86 Construction: Diecast metal body, metal base, Real Riders rubber tyres Packaging: sealed on the original Hot Wheels premium blister card Manufacturer age grade: 3 years and up (Mattel official). 100% authentic — imported and hand-verified by DiecastBD. | U12: 1 x Hot Wheels Car Culture — Nissan Skyline 2000GT-R LBWK (Japan Historics), sealed on the original Hot Wheels premium blister card | V12: No manufacturer or seller warranty is offered on collectible diecast models. Every piece is supplied factory-sealed in its original packaging, is 100% authentic, and is hand-inspected before dispatch. Report any transit damage with the unopened parcel on delivery. | W12: কালেক্টিবল ডাইকাস্ট মডেলের ক্ষেত্রে কোনো ম্যানুফ্যাকচারার বা সেলার ওয়ারেন্টি দেওয়া হয় না। প্রতিটি পিস অরিজিনাল প্যাকেজিংয়ে ফ্যাক্টরি-সিলড অবস্থায় সরবরাহ করা হয়, ১০০% আসল, এবং পাঠানোর আগে হাতে যাচাই করা হয়। ডেলিভারির সময় পার্সেল না খুলে ট্রানজিটে কোনো ক্ষতি হয়ে থাকলে সঙ্গে সঙ্গে জানান। | X12: No Warranty | Z12: 0.2 | AA12: 18 | AB12: 15 | AC12: 6 | AD12: Dark Blue | AE12: DCBD-HWCC-008 | AF12: DCBD-HWCC-008 | AG12: https://cdn.cartup.com/product/480da80f-7c29-4561-a908-4581f0f8841b.webp | AH12: 1 | AI12: 1890 | AJ12: 1770 | AK12: 46231 | AL12: 46596.999
A13: Hot Wheels Car Culture — LB-Kaido Works Nissan Skyline GT-R R32 (Aero Styles) | B13: Hot Wheels Car Culture — LB-Kaido Works Nissan Skyline GT-R R32 ১:৬৪ ডাইকাস্ট মডেল কার (Aero Styles) | C13: https://cdn.cartup.com/product/375e5a3e-b231-4b51-97b0-619fba461cc6.webp | L13: No Brand | M13: PCS | N13: jdm, nissan, skyline, r32, gt-r, lbwk, kaido works, aero styles, godzilla | O13: 10 Years+ | P13: Alloy | Q13: Aero Styles premium series; LB-Kaido Works widebody; Real Riders rubber tyres | R13: Aero Styles প্রিমিয়াম সিরিজ; LB-Kaido Works ওয়াইডবডি; Real Riders রাবার টায়ার | S13: LB-Kaido Works ওয়াইডবডি R32, পরিচ্ছন্ন সাদা রেস ট্রিমে — একদম নতুন Aero Styles সিরিজের হিরো কার। মেটাল বডি ও মেটাল বেস, Real Riders রাবার টায়ার। স্কেল: 1:64 · প্রস্তুতকারক: Mattel · সিরিজ: Car Culture — Aero Styles · মডেল নম্বর: FPY86 গঠন: Diecast metal body, metal base, Real Riders rubber tyres প্যাকেজিং: অরিজিনাল Hot Wheels প্রিমিয়াম ব্লিস্টার কার্ডে সিলড প্রস্তুতকারকের বয়সসীমা: ৩ বছর ও তদূর্ধ্ব (Mattel অফিসিয়াল)। ১০০% আসল — DiecastBD কর্তৃক আমদানিকৃত ও হাতে যাচাইকৃত। | T13: LB-Kaido Works widebody R32 in clean white race trim — the hero car of the brand-new Aero Styles series. Metal/metal, Real Riders. Scale: 1:64 · Manufacturer: Mattel · Series: Car Culture — Aero Styles · Model no: FPY86 Construction: Diecast metal body, metal base, Real Riders rubber tyres Packaging: sealed on the original Hot Wheels premium blister card Manufacturer age grade: 3 years and up (Mattel official). 100% authentic — imported and hand-verified by DiecastBD. | U13: 1 x Hot Wheels Car Culture — LB-Kaido Works Nissan Skyline GT-R R32 (Aero Styles), sealed on the original Hot Wheels premium blister card | V13: No manufacturer or seller warranty is offered on collectible diecast models. Every piece is supplied factory-sealed in its original packaging, is 100% authentic, and is hand-inspected before dispatch. Report any transit damage with the unopened parcel on delivery. | W13: কালেক্টিবল ডাইকাস্ট মডেলের ক্ষেত্রে কোনো ম্যানুফ্যাকচারার বা সেলার ওয়ারেন্টি দেওয়া হয় না। প্রতিটি পিস অরিজিনাল প্যাকেজিংয়ে ফ্যাক্টরি-সিলড অবস্থায় সরবরাহ করা হয়, ১০০% আসল, এবং পাঠানোর আগে হাতে যাচাই করা হয়। ডেলিভারির সময় পার্সেল না খুলে ট্রানজিটে কোনো ক্ষতি হয়ে থাকলে সঙ্গে সঙ্গে জানান। | X13: No Warranty | Z13: 0.2 | AA13: 18 | AB13: 15 | AC13: 6 | AD13: White | AE13: DCBD-HWCC-009 | AF13: DCBD-HWCC-009 | AG13: https://cdn.cartup.com/product/375e5a3e-b231-4b51-97b0-619fba461cc6.webp | AH13: 3 | AI13: 2390 | AJ13: 2230 | AK13: 46231 | AL13: 46596.999
A14: Hot Wheels Car Culture — 2008 Audi A4 DTM Touring Car (Aero Styles) | B14: Hot Wheels Car Culture — 2008 Audi A4 DTM ১:৬৪ ডাইকাস্ট মডেল কার (Aero Styles) | C14: https://cdn.cartup.com/product/1580fb8a-5afd-4058-ac12-2604ff981728.webp | L14: No Brand | M14: PCS | N14: car culture, audi, a4, dtm, aero styles, motorsport | O14: 10 Years+ | P14: Alloy | Q14: Aero Styles premium series; Metal body & metal base; Real Riders rubber tyres | R14: Aero Styles প্রিমিয়াম সিরিজ; মেটাল বডি ও মেটাল বেস; Real Riders রাবার টায়ার | S14: ২০০৮ সালের Audi A4 DTM টুরিং কার, গাঢ় কালো রঙে — প্রিমিয়াম Aero Styles কার্ডে মোটরস্পোর্টের ঐতিহ্য। স্কেল: 1:64 · প্রস্তুতকারক: Mattel · সিরিজ: Car Culture — Aero Styles · মডেল নম্বর: FPY86 গঠন: Diecast metal body, metal base, Real Riders rubber tyres প্যাকেজিং: অরিজিনাল Hot Wheels প্রিমিয়াম ব্লিস্টার কার্ডে সিলড প্রস্তুতকারকের বয়সসীমা: ৩ বছর ও তদূর্ধ্ব (Mattel অফিসিয়াল)। ১০০% আসল — DiecastBD কর্তৃক আমদানিকৃত ও হাতে যাচাইকৃত। | T14: 2008 Audi A4 DTM touring car in menacing black — motorsport pedigree on a premium Aero Styles card. Scale: 1:64 · Manufacturer: Mattel · Series: Car Culture — Aero Styles · Model no: FPY86 Construction: Diecast metal body, metal base, Real Riders rubber tyres Packaging: sealed on the original Hot Wheels premium blister card Manufacturer age grade: 3 years and up (Mattel official). 100% authentic — imported and hand-verified by DiecastBD. | U14: 1 x Hot Wheels Car Culture — 2008 Audi A4 DTM Touring Car (Aero Styles), sealed on the original Hot Wheels premium blister card | V14: No manufacturer or seller warranty is offered on collectible diecast models. Every piece is supplied factory-sealed in its original packaging, is 100% authentic, and is hand-inspected before dispatch. Report any transit damage with the unopened parcel on delivery. | W14: কালেক্টিবল ডাইকাস্ট মডেলের ক্ষেত্রে কোনো ম্যানুফ্যাকচারার বা সেলার ওয়ারেন্টি দেওয়া হয় না। প্রতিটি পিস অরিজিনাল প্যাকেজিংয়ে ফ্যাক্টরি-সিলড অবস্থায় সরবরাহ করা হয়, ১০০% আসল, এবং পাঠানোর আগে হাতে যাচাই করা হয়। ডেলিভারির সময় পার্সেল না খুলে ট্রানজিটে কোনো ক্ষতি হয়ে থাকলে সঙ্গে সঙ্গে জানান। | X14: No Warranty | Z14: 0.2 | AA14: 18 | AB14: 15 | AC14: 6 | AD14: Black | AE14: DCBD-HWCC-010 | AF14: DCBD-HWCC-010 | AG14: https://cdn.cartup.com/product/1580fb8a-5afd-4058-ac12-2604ff981728.webp | AH14: 1 | AI14: 2100 | AJ14: 1960 | AK14: 46231 | AL14: 46596.999
... A31: MINI GT Toyota Supra A80 Top Secret GT-300 — Red | B31: MINI GT Toyota Supra A80 Top Secret GT-300 লাল ১:৬৪ ডাইকাস্ট মডেল কার | C31: https://cdn.cartup.com/product/192b9e00-4edd-47ff-90a1-7e49220ea4bb.webp | L31: No Brand | M31: PCS | N31: jdm, toyota, supra, top secret, mini gt, tsm, bd exclusive | O31: 18 Years+ | P31: Alloy | Q31: TSM Models premium build; Top Secret GT-300 livery; Rubber tyres; Collector display box | R31: TSM Models প্রিমিয়াম বিল্ড; Top Secret GT-300 লিভারি; রাবার টায়ার; কালেক্টর ডিসপ্লে বক্স | S31: Smokey Nagata-র Top Secret GT-300 Supra — যে টিউনার কিংবদন্তি সাধারণ রাস্তায় ৩০০ কিমি/ঘণ্টা গতি তুলেছিল। MINI GT-র দ্রুততম বিক্রি হওয়া JDM রিলিজগুলোর একটি। স্কেল: 1:64 · প্রস্তুতকারক: TSM Models · সিরিজ: MINI GT 1:64 Collection · মডেল নম্বর: MGT01132 গঠন: Diecast metal body, rubber tyres, detailed interior প্যাকেজিং: অরিজিনাল MINI GT কালেক্টর ডিসপ্লে বক্সে প্রস্তুতকারকের বয়সসীমা: ১৪ বছর ও তদূর্ধ্ব (TSM Models অফিসিয়াল)। ১০০% আসল — DiecastBD কর্তৃক আমদানিকৃত ও হাতে যাচাইকৃত। | T31: Smokey Nagata's Top Secret GT-300 Supra — the tuner legend that ran 300km/h on public roads. One of the fastest-moving MINI GT JDM releases. Scale: 1:64 · Manufacturer: TSM Models · Series: MINI GT 1:64 Collection · Model no: MGT01132 Construction: Diecast metal body, rubber tyres, detailed interior Packaging: in the original MINI GT collector display box Manufacturer age grade: 14 years and over (TSM Models official). 100% authentic — imported and hand-verified by DiecastBD. | U31: 1 x MINI GT Toyota Supra A80 Top Secret GT-300 — Red, in the original MINI GT collector display box | V31: No manufacturer or seller warranty is offered on collectible diecast models. Every piece is supplied factory-sealed in its original packaging, is 100% authentic, and is hand-inspected before dispatch. Report any transit damage with the unopened parcel on delivery. | W31: কালেক্টিবল ডাইকাস্ট মডেলের ক্ষেত্রে কোনো ম্যানুফ্যাকচারার বা সেলার ওয়ারেন্টি দেওয়া হয় না। প্রতিটি পিস অরিজিনাল প্যাকেজিংয়ে ফ্যাক্টরি-সিলড অবস্থায় সরবরাহ করা হয়, ১০০% আসল, এবং পাঠানোর আগে হাতে যাচাই করা হয়। ডেলিভারির সময় পার্সেল না খুলে ট্রানজিটে কোনো ক্ষতি হয়ে থাকলে সঙ্গে সঙ্গে জানান। | X31: No Warranty | Z31: 0.2 | AA31: 13 | AB31: 9 | AC31: 6 | AD31: Red | AE31: DCBD-MGT-TS01 | AF31: DCBD-MGT-TS01 | AG31: https://cdn.cartup.com/product/192b9e00-4edd-47ff-90a1-7e49220ea4bb.webp | AH31: 2 | AI31: 2780 | AJ31: 2600 | AK31: 46231 | AL31: 46596.999

Sheet value_hidden
A1: Name | B1: Value | C1: Name | D1: Value | E1: Name | F1: Value | G1: Name | H1: Value | I1: Name | J1: Value | K1: Name | L1: Value | M1: Name | N1: Value
A2: Dettol | B2: 2 | C2: PCS | D2: 2 | E2: 0+ Months | F2: 381 | G2: Tweed | H2: 14668 | I2: Seller Warranty | J2: 1 | K2: 1 month | L2: 4 | M2: Signature Black | N2: 11512
A3: MAYBELLINE | B3: 3 | C3: Gram | D3: 3 | E3: 0-3 Months | F3: 382 | G3: Partex Board | H3: 14669 | I3: Brand Warranty | J3: 2 | K3: 2 month | L3: 5 | M3: Can | N3: 11627
A4: Samsung | B4: 411 | C4: Meter | D4: 4 | E4: 0-6 Months | F4: 383 | G4: Metal Frame | H4: 14670 | I4: No Warranty | J4: 3 | K4: 3 month | L4: 6 | M4: Type 5 | N4: 11842
A5: Rolex | B5: 412 | C5: Dozen | D5: 5 | E5: 6-12 Months | F5: 384 | G5: Carbon Steel | H5: 14671 | K5: 4 month | L5: 7 | M5: Purifying Charcoal | N5: 11843
A6: Honda | B6: 413 | C6: Hali | D6: 6 | E6: 1-2 Years | F6: 385 | G6: Fabric and Plastic | H6: 14672 | K6: 5 month | L6: 8 | M6: Australian Tea Tree | N6: 11844
A7: Suzuki | B7: 415 | C7: kilogram | D7: 7 | E7: 2-3 Years | F7: 386 | G7: Katan | H7: 14673 | K7: 6 month | L7: 9 | M7: Deep Cleansing | N7: 11845
A8: Pakiza | B8: 416 | C8: Miligrams | D8: 21 | E8: 3-4 Years | F8: 387 | G8: Jersey | H8: 14674 | K8: 7 month | L8: 10 | M8: Rotary | N8: 11846
A9: Home Tex | B9: 417 | C9: Litre | D9: 34 | E9: 4-5 Years | F9: 388 | G9: Georgette | H9: 14675 | K9: 8 month | L9: 11 | M9: Wave | N9: 11847
A10: Walton | B10: 418 | C10: Pairs | D10: 35 | E10: 5-7 Years | F10: 389 | G10: Half Silk | H10: 14676 | K10: 9 month | L10: 12 | M10: Point | N10: 11848
A11: Apple | B11: 419 | C11: K.M. | D11: 36 | E11: 7-9 Years | F11: 390 | G11: Polycarbonate | H11: 14677 | K11: 10 month | L11: 13 | M11: Type B | N11: 11849
A12: Canon | B12: 420 | E12: 9-12 Years | F12: 391 | G12: Acetate | H12: 14678 | K12: 11 month | L12: 14 | M12: Type A | N12: 11850
A13: RFL | B13: 421 | E13: 10 Years+ | F13: 392 | G13: Sheet Metal | H13: 14679 | K13: 18 month | L13: 15 | M13: 9*1.75in | N13: 11851
A14: Regal | B14: 422 | E14: 18 Years+ | F14: 393 | G14: Steel | H14: 14680 | K14: 1 year | L14: 16 | M14: 9*2.0in | N14: 11852
A15: Deli | B15: 423 | E15: 1-3 Years | F15: 10019 | G15: Foam | H15: 14681 | K15: 2 year | L15: 17 | M15: Soft | N15: 11853
A16: OnePlus | B16: 424 | G16: PE Foam | H16: 14682 | K16: 3 year | L16: 18 | M16: 90 Tablets | N16: 11854
A17: String | B17: 427 | G17: Fabric | H17: 14683 | K17: 4 year | L17: 19 | M17: 30 Tablets | N17: 11855
A18: Redragon | B18: 431 | G18: Sheet Metal | H18: 14684 | K18: 5 year | L18: 20 | M18: Herbs | N18: 11856
A19: Fantech | B19: 432 | G19: Particle Board | H19: 14685 | K19: 6 year | L19: 21 | M19: Lemongrass | N19: 11857
A20: A4tech | B20: 433 | G20: Jute | H20: 14686 | K20: 7 year | L20: 22 | M20: 25mm | N20: 11858
A21: Logitech | B21: 434 | G21: Acrylic | H21: 14687 | K21: 8 year | L21: 23 | M21: 1 Inch | N21: 11859
A22: GoGo | B22: 435 | G22: Plush | H22: 14688 | K22: 10 year | L22: 24 | M22: 30mm | N22: 11860
A23: Dior | B23: 484 | G23: Artificial Leather | H23: 14689 | K23: 12 year | L23: 25 | M23: 1.2 Inch | N23: 11861
A24: Backpackers | B24: 485 | G24: Velvet | H24: 14690 | K24: 15 year | L24: 26 | M24: Full Box | N24: 11862
A25: Kawasaki | B25: 486 | G25: Sponge | H25: 14691 | K25: 25 year | L25: 27 | M25: Pack 1 | N25: 11513
A26: Audi | B26: 487 | G26: Polypropylene | H26: 14692 | K26: 30 year | L26: 28 | M26: Pack 2 | N26: 11514
A27: Panasonic | B27: 488 | G27: Cast Iron | H27: 14693 | K27: Life Time | L27: 29 | M27: pack 3 | N27: 11515
A28: Jaynal's Brand | B28: 489 | G28: Microfiber | H28: 14694 | M28: EU 32 | N28: 11516
A29: Test Dev | B29: 490 | G29: Ceramic | H29: 14695 | M29: EU 36 | N29: 11517
A30: Test Brand1 | B30: 491 | G30: Elastic Fiber | H30: 14696 | M30: EU 34 | N30: 11518
A31: MDK | B31: 492 | G31: Lead Crystal | H31: 14697 | M31: EU 38 | N31: 11519
A32: Herlan | B32: 516 | G32: Polycarbonate | H32: 14698 | M32: EU 28 | N32: 11520
A33: Olevs | B33: 517 | G33: Twill | H33: 14699 | M33: EU 30 | N33: 11521
A34: Parachute | B34: 518 | G34: Oak | H34: 14700 | M34: EU 31 | N34: 11522
A35: No Brand | B35: 519 | G35: Shegun Wood | H35: 14701 | M35: 200 Pcs | N35: 11628
A36: Agrey Hometex | B36: 520 | G36: Other | H36: 14702 | M36: 1.75MM | N36: 11863
A37: Proclean | B37: 521 | G37: Ply-wood | H37: 14703 | M37: .50MM | N37: 11864
A38: SSB Leather | B38: 522 | G38: Canadian Processed Wood | H38: 14704 | M38: .25MM | N38: 11865
A39: NAVIFORCE | B39: 523 | G39: Aluminium | H39: 14705 | M39: .75MM | N39: 11866
... A114: EXS | B114: 598 | G114: Dobby cotton | H114: 26999 | M114: 2-storey cage 24/24/18 size | N114: 11532
A115: Manhood | B115: 599 | M115: 3-compartment welded cage | N115: 11533
A116: Kohinoor | B116: 600 | M116: 3-compartment net cage 24/18/14 | N116: 11534
A117: RECARE | B117: 601 | M117: 3-compartment net cage 24/24/18 | N117: 11535
A118: D'sire | B118: 602 | M118: 3-storey cage 24/18/14 size | N118: 11536
A119: Skore | B119: 603 | M119: 3-storey cage 24/24/18 size | N119: 11537
A120: Fire | B120: 604 | M120: 4-compartment welded cage | N120: 11538
A121: D'lay | B121: 605 | M121: 4-compartment net cage 24/18/14 | N121: 11539
A122: Skins | B122: 606 | M122: 4-compartment net cage 24/24/18 | N122: 11540
A123: Xpression | B123: 607 | M123: 4-storey cage 24/18/14 size | N123: 11541
A124: Thrill | B124: 608 | M124: 4-storey cage 24/24/18 size | N124: 11542
A125: Version | B125: 609 | M125: 6-compartment cage 24/18/14 size | N125: 11543
A126: Playgard | B126: 610 | M126: 6-compartment net system cage | N126: 11544
... A3403: Sera | B3403: 3917 | M3403: RossoCorsa-PumaBlack-PumaWhite | N3403: 11292
M3404: PumaBlack-PumaBlack | N3404: 11293
M3405: PumaBlack-LavaBlast | N3405: 11294
M3406: Quarry-PumaWhite | N3406: 11295
M3407: DarkGray-Black-White | N3407: 11296
M3408: Black-Red-Yellow | N3408: 11297
M3409: Lake Blue-Blazing Blue | N3409: 11298
M3410: Peacoat-White | N3410: 11299
M3411: Black-HighRiskRed | N3411: 11300
M3412: Black-Lime-Sapphire | N3412: 11301
M3413: Black-Nrgy Peach | N3413: 11302
M3414: Lime-Black-White | N3414: 11303
M3415: 800 gm | N3415: 11617
... M16273: Cigar | N16273: 27163

Sheet payload_hidden
A1: nameEn | B1: nameBn | C1: image1 | D1: image2 | E1: image3 | F1: image4 | G1: image5 | H1: image6 | I1: image7 | J1: image8 | K1: videoUrl | L1: brandId | M1: unitId | N1: tags | O1: product_attribute_7 | P1: product_attribute_6 | Q1: hightlight_en | R1: hightlight_bn | S1: description_bn | T1: description_en | U1: inthebox | V1: warrantyPolicyEn | W1: warrantyPolicyBn | X1: warrantyType | Y1: warrantyPeriod | Z1: packageWeightInKg | AA1: packageLengthInCm | AB1: packageWidthInCm | AC1: packageHeightInCm | AD1: variant_attribute_14 | AE1: sellerSku | AF1: parentSku | AG1: variantImage | AH1: currentStockQty | AI1: price | AJ1: promoPrice | AK1: promoStartAt | AL1: promoEndAt | AM1: freeItems | AN1: category_attribute_8265
A2: ==IF(product!A3<>"",product!A3,"") -> Hot Wheels Ferrari 5-Pack (Sealed) | B2: ==IF(product!B3<>"",product!B3,"") -> Hot Wheels Ferrari 5-Pack (সিলড) — ১:৬৪ ডাইকাস্ট মডেল কার সেট | C2: ==IF(product!C3<>"",product!C3,"") -> https://cdn.cartup.com/product/32443a23-ff9d-46a5-bb4c-a70a6d426705.webp | D2: ==IF(product!D3<>"",product!D3,"") | E2: ==IF(product!E3<>"",product!E3,"") | F2: ==IF(product!F3<>"",product!F3,"") | G2: ==IF(product!G3<>"",product!G3,"") | H2: ==IF(product!H3<>"",product!H3,"") | ... K2: ==IF(product!K3<>"",product!K3,"") | L2: ==IF('product'!L3<>"", VLOOKUP('product'!L3,product_attribute_1[#All],2,FALSE),"") -> 519 | M2: ==IF('product'!M3<>"", VLOOKUP('product'!M3,product_attribute_2[#All],2,FALSE),"") -> 2 | N2: ==IF(product!N3<>"",product!N3,"") -> ferrari, 5-pack, sealed, multi-pack, gift | O2: ==IF('product'!O3<>"", VLOOKUP('product'!O3,product_attribute_7[#All],2,FALSE),"") -> 392 | P2: ==IF('product'!P3<>"", VLOOKUP('product'!P3,product_attribute_6[#All],2,FALSE),"") -> 14776 | Q2: ==IF(product!Q3<>"",product!Q3,"") -> Sealed 5-car Ferrari set; Officially licensed Ferrari liveries; Collectible sealed packaging | R2: ==IF(product!R3<>"",product!R3,"") -> সিলড ৫টি Ferrari গাড়ির সেট; অফিসিয়াল লাইসেন্সপ্রাপ্ত Ferrari লিভারি; সংগ্রাহকদের জন্য সিলড প্যাকেজিং | S2: ==IF(product!S3<>"",product!S3,"") -> সিলড ৫টি Ferrari গাড়ির সেট — Hot Wheels-এ Ferrari-র প্রত্যাবর্তন উপলক্ষে। সেটে আছে F40, SF90, 12Cilindri, Dino এবং 365 GTB/4। সিলড প্যাক একইসঙ্গে ডিসপ্লে পিস এবং সময়ের সঙ্গে দাম বাড়া কালেক্টিবল। স্কেল: 1:64 · প্রস্তুতকারক: Mattel · সিরিজ: Ferrari 5-Pack 2025 · মডেল নম্বর: JLN12 গঠন: Diecast metal body, plastic base, plastic wheels প্যাকেজিং: অরিজিনাল Hot Wheels ৫-প্যাক বক্সে সিলড প্রস্তুতকারকের বয়সসীমা: ৩ বছর ও তদূর্ধ্ব (Mattel অফিসিয়াল)। ১০০% আসল — DiecastBD কর্তৃক আমদানিকৃত ও হাতে যাচাইকৃত। | T2: ==IF(product!T3<>"",product!T3,"") -> Sealed 5-car Ferrari set marking Ferrari's return to Hot Wheels — F40, SF90, 12Cilindri, Dino and 365 GTB/4. Sealed packs are both a display piece and an appreciating collectible. Scale: 1:64 · Manufacturer: Mattel · Series: Ferrari 5-Pack 2025 · Model no: JLN12 Construction: Diecast metal body, plastic base, plastic wheels Packaging: sealed in the original Hot Wheels 5-pack box Manufacturer age grade: 3 years and up (Mattel official). 100% authentic — imported and hand-verified by DiecastBD. | U2: ==IF(product!U3<>"",product!U3,"") -> 1 x Hot Wheels Ferrari 5-Pack (Sealed), sealed in the original Hot Wheels 5-pack box (contains 5 x 1:64 diecast vehicles) | V2: ==IF(product!V3<>"",product!V3,"") -> No manufacturer or seller warranty is offered on collectible diecast models. Every piece is supplied factory-sealed in its original packaging, is 100% authentic, and is hand-inspected before dispatch. Report any transit damage with the unopened parcel on delivery. | W2: ==IF(product!W3<>"",product!W3,"") -> কালেক্টিবল ডাইকাস্ট মডেলের ক্ষেত্রে কোনো ম্যানুফ্যাকচারার বা সেলার ওয়ারেন্টি দেওয়া হয় না। প্রতিটি পিস অরিজিনাল প্যাকেজিংয়ে ফ্যাক্টরি-সিলড অবস্থায় সরবরাহ করা হয়, ১০০% আসল, এবং পাঠানোর আগে হাতে যাচাই করা হয়। ডেলিভারির সময় পার্সেল না খুলে ট্রানজিটে কোনো ক্ষতি হয়ে থাকলে সঙ্গে সঙ্গে জানান। | X2: ==IF('product'!X3<>"", VLOOKUP('product'!X3,product_attribute_100[#All],2,FALSE),"") -> 3 | Y2: ==IF('product'!Y3<>"", VLOOKUP('product'!Y3,product_attribute_101[#All],2,FALSE),"") | Z2: ==IF(product!Z3<>"",product!Z3,"") -> 0.5 | AA2: ==IF(product!AA3<>"",product!AA3,"") -> 28 | AB2: ==IF(product!AB3<>"",product!AB3,"") -> 20 | AC2: ==IF(product!AC3<>"",product!AC3,"") -> 7 | AD2: ==IF('product'!AD3<>"", VLOOKUP('product'!AD3,product_attribute_14[#All],2,FALSE),"") -> 561 | AE2: ==IF(product!AE3<>"",product!AE3,"") -> DCBD-HW5P-001 | AF2: ==IF(product!AF3<>"",product!AF3,"") -> DCBD-HW5P-001 | AG2: ==IF(product!AG3<>"",product!AG3,"") -> https://cdn.cartup.com/product/32443a23-ff9d-46a5-bb4c-a70a6d426705.webp | AH2: ==IF(product!AH3<>"",product!AH3,"") -> 4 | AI2: ==IF(product!AI3<>"",product!AI3,"") -> 3400 | AJ2: ==IF(product!AJ3<>"",product!AJ3,"") -> 3180 | AK2: ==IF(product!AK3<>"",product!AK3,"") -> 46231 | AL2: ==IF(product!AL3<>"",product!AL3,"") -> 46596.999 | AM2: ==IF(product!AM3<>"",product!AM3,"")
A3: ==IF(product!A4<>"",product!A4,"") -> Hot Wheels Formula 1 5-Pack (Sealed) | B3: ==IF(product!B4<>"",product!B4,"") -> Hot Wheels Formula 1 5-Pack (সিলড) — ১:৬৪ ডাইকাস্ট মডেল কার সেট | C3: ==IF(product!C4<>"",product!C4,"") -> https://cdn.cartup.com/product/0b3f8fe3-68b6-48a6-93fd-d62a27f081b6.webp | D3: ==IF(product!D4<>"",product!D4,"") | E3: ==IF(product!E4<>"",product!E4,"") | F3: ==IF(product!F4<>"",product!F4,"") | G3: ==IF(product!G4<>"",product!G4,"") | H3: ==IF(product!H4<>"",product!H4,"") | ... K3: ==IF(product!K4<>"",product!K4,"") | L3: ==IF('product'!L4<>"", VLOOKUP('product'!L4,product_attribute_1[#All],2,FALSE),"") -> 519 | M3: ==IF('product'!M4<>"", VLOOKUP('product'!M4,product_attribute_2[#All],2,FALSE),"") -> 2 | N3: ==IF(product!N4<>"",product!N4,"") -> f1, formula 1, 5-pack, sealed, multi-pack, gift | O3: ==IF('product'!O4<>"", VLOOKUP('product'!O4,product_attribute_7[#All],2,FALSE),"") -> 392 | P3: ==IF('product'!P4<>"", VLOOKUP('product'!P4,product_attribute_6[#All],2,FALSE),"") -> 14776 | Q3: ==IF(product!Q4<>"",product!Q4,"") -> Sealed 5-car F1 grid set; 5 official F1 team liveries; Great gift for F1 fans | R3: ==IF(product!R4<>"",product!R4,"") -> সিলড ৫টি F1 গাড়ির গ্রিড সেট; ৫টি অফিসিয়াল F1 টিম লিভারি; F1 ভক্তদের জন্য দারুণ উপহার | S3: ==IF(product!S4<>"",product!S4,"") -> সিলড ৫টি F1 গ্রিড সেট: Oracle Red Bull, Mercedes-AMG Petronas, BWT Alpine, MoneyGram Haas এবং Atlassian Williams। যেকোনো F1 ভক্তের জন্য সবচেয়ে সহজ উপহার। স্কেল: 1:64 · প্রস্তুতকারক: Mattel · সিরিজ: Formula 1 5-Pack 2025 · মডেল নম্বর: JLN11 গঠন: Diecast metal body, plastic base, plastic wheels প্যাকেজিং: অরিজিনাল Hot Wheels ৫-প্যাক বক্সে সিলড প্রস্তুতকারকের বয়সসীমা: ৩ বছর ও তদূর্ধ্ব (Mattel অফিসিয়াল)। ১০০% আসল — DiecastBD কর্তৃক আমদানিকৃত ও হাতে যাচাইকৃত। | T3: ==IF(product!T4<>"",product!T4,"") -> Sealed 5-car F1 grid set: Oracle Red Bull, Mercedes-AMG Petronas, BWT Alpine, MoneyGram Haas and Atlassian Williams. The easiest gift-in for any F1 fan. Scale: 1:64 · Manufacturer: Mattel · Series: Formula 1 5-Pack 2025 · Model no: JLN11 Construction: Diecast metal body, plastic base, plastic wheels Packaging: sealed in the original Hot Wheels 5-pack box Manufacturer age grade: 3 years and up (Mattel official). 100% authentic — imported and hand-verified by DiecastBD. | U3: ==IF(product!U4<>"",product!U4,"") -> 1 x Hot Wheels Formula 1 5-Pack (Sealed), sealed in the original Hot Wheels 5-pack box (contains 5 x 1:64 diecast vehicles) | V3: ==IF(product!V4<>"",product!V4,"") -> No manufacturer or seller warranty is offered on collectible diecast models. Every piece is supplied factory-sealed in its original packaging, is 100% authentic, and is hand-inspected before dispatch. Report any transit damage with the unopened parcel on delivery. | W3: ==IF(product!W4<>"",product!W4,"") -> কালেক্টিবল ডাইকাস্ট মডেলের ক্ষেত্রে কোনো ম্যানুফ্যাকচারার বা সেলার ওয়ারেন্টি দেওয়া হয় না। প্রতিটি পিস অরিজিনাল প্যাকেজিংয়ে ফ্যাক্টরি-সিলড অবস্থায় সরবরাহ করা হয়, ১০০% আসল, এবং পাঠানোর আগে হাতে যাচাই করা হয়। ডেলিভারির সময় পার্সেল না খুলে ট্রানজিটে কোনো ক্ষতি হয়ে থাকলে সঙ্গে সঙ্গে জানান। | X3: ==IF('product'!X4<>"", VLOOKUP('product'!X4,product_attribute_100[#All],2,FALSE),"") -> 3 | Y3: ==IF('product'!Y4<>"", VLOOKUP('product'!Y4,product_attribute_101[#All],2,FALSE),"") | Z3: ==IF(product!Z4<>"",product!Z4,"") -> 0.5 | AA3: ==IF(product!AA4<>"",product!AA4,"") -> 28 | AB3: ==IF(product!AB4<>"",product!AB4,"") -> 20 | AC3: ==IF(product!AC4<>"",product!AC4,"") -> 7 | AD3: ==IF('product'!AD4<>"", VLOOKUP('product'!AD4,product_attribute_14[#All],2,FALSE),"") -> 605 | AE3: ==IF(product!AE4<>"",product!AE4,"") -> DCBD-HW5P-002 | AF3: ==IF(product!AF4<>"",product!AF4,"") -> DCBD-HW5P-002 | AG3: ==IF(product!AG4<>"",product!AG4,"") -> https://cdn.cartup.com/product/0b3f8fe3-68b6-48a6-93fd-d62a27f081b6.webp | AH3: ==IF(product!AH4<>"",product!AH4,"") -> 2 | AI3: ==IF(product!AI4<>"",product!AI4,"") -> 2550 | AJ3: ==IF(product!AJ4<>"",product!AJ4,"") -> 2380 | AK3: ==IF(product!AK4<>"",product!AK4,"") -> 46231 | AL3: ==IF(product!AL4<>"",product!AL4,"") -> 46596.999 | AM3: ==IF(product!AM4<>"",product!AM4,"")
A4: ==IF(product!A5<>"",product!A5,"") -> Hot Wheels Car Culture — Ferrari 250 GTO (Vintage Racing Club) | B4: ==IF(product!B5<>"",product!B5,"") -> Hot Wheels Car Culture — Ferrari 250 GTO ১:৬৪ ডাইকাস্ট মডেল কার (Vintage Racing Club) | C4: ==IF(product!C5<>"",product!C5,"") -> https://cdn.cartup.com/product/2f33e0a9-85a1-41cf-9c96-530c9264408e.webp | D4: ==IF(product!D5<>"",product!D5,"") | E4: ==IF(product!E5<>"",product!E5,"") | F4: ==IF(product!F5<>"",product!F5,"") | G4: ==IF(product!G5<>"",product!G5,"") | H4: ==IF(product!H5<>"",product!H5,"") | ... K4: ==IF(product!K5<>"",product!K5,"") | L4: ==IF('product'!L5<>"", VLOOKUP('product'!L5,product_attribute_1[#All],2,FALSE),"") -> 519 | M4: ==IF('product'!M5<>"", VLOOKUP('product'!M5,product_attribute_2[#All],2,FALSE),"") -> 2 | N4: ==IF(product!N5<>"",product!N5,"") -> car culture, ferrari, 250 gto, vintage racing, classic | O4: ==IF('product'!O5<>"", VLOOKUP('product'!O5,product_attribute_7[#All],2,FALSE),"") -> 392 | P4: ==IF('product'!P5<>"", VLOOKUP('product'!P5,product_attribute_6[#All],2,FALSE),"") -> 14776 | Q4: ==IF(product!Q5<>"",product!Q5,"") -> Car Culture premium series; Metal body & metal base; Real Riders rubber tyres | R4: ==IF(product!R5<>"",product!R5,"") -> Car Culture প্রিমিয়াম সিরিজ; মেটাল বডি ও মেটাল বেস; Real Riders রাবার টায়ার | S4: ==IF(product!S5<>"",product!S5,"") -> Ferrari 250 GTO — পৃথিবীর সবচেয়ে দামি গাড়ি (একটি আসল গাড়ি ৭ কোটি ডলারে বিক্রি হয়েছে)। Car Culture প্রিমিয়াম বিল্ড, মেটাল বেস ও Real Riders রাবার টায়ার সহ। স্কেল: 1:64 · প্রস্তুতকারক: Mattel · সিরিজ: Car Culture — Vintage Racing Club · মডেল নম্বর: FPY86 গঠন: Diecast metal body, metal base, Real Riders rubber tyres প্যাকেজিং: অরিজিনাল Hot Wheels প্রিমিয়াম ব্লিস্টার কার্ডে সিলড প্রস্তুতকারকের বয়সসীমা: ৩ বছর ও তদূর্ধ্ব (Mattel অফিসিয়াল)। ১০০% আসল — DiecastBD কর্তৃক আমদানিকৃত ও হাতে যাচাইকৃত। | T4: ==IF(product!T5<>"",product!T5,"") -> The Ferrari 250 GTO — the most valuable car on earth (a real one sold for $70M). Car Culture premium with metal base and Real Riders. Scale: 1:64 · Manufacturer: Mattel · Series: Car Culture — Vintage Racing Club · Model no: FPY86 Construction: Diecast metal body, metal base, Real Riders rubber tyres Packaging: sealed on the original Hot Wheels premium blister card Manufacturer age grade: 3 years and up (Mattel official). 100% authentic — imported and hand-verified by DiecastBD. | U4: ==IF(product!U5<>"",product!U5,"") -> 1 x Hot Wheels Car Culture — Ferrari 250 GTO (Vintage Racing Club), sealed on the original Hot Wheels premium blister card | V4: ==IF(product!V5<>"",product!V5,"") -> No manufacturer or seller warranty is offered on collectible diecast models. Every piece is supplied factory-sealed in its original packaging, is 100% authentic, and is hand-inspected before dispatch. Report any transit damage with the unopened parcel on delivery. | W4: ==IF(product!W5<>"",product!W5,"") -> কালেক্টিবল ডাইকাস্ট মডেলের ক্ষেত্রে কোনো ম্যানুফ্যাকচারার বা সেলার ওয়ারেন্টি দেওয়া হয় না। প্রতিটি পিস অরিজিনাল প্যাকেজিংয়ে ফ্যাক্টরি-সিলড অবস্থায় সরবরাহ করা হয়, ১০০% আসল, এবং পাঠানোর আগে হাতে যাচাই করা হয়। ডেলিভারির সময় পার্সেল না খুলে ট্রানজিটে কোনো ক্ষতি হয়ে থাকলে সঙ্গে সঙ্গে জানান। | X4: ==IF('product'!X5<>"", VLOOKUP('product'!X5,product_attribute_100[#All],2,FALSE),"") -> 3 | Y4: ==IF('product'!Y5<>"", VLOOKUP('product'!Y5,product_attribute_101[#All],2,FALSE),"") | Z4: ==IF(product!Z5<>"",product!Z5,"") -> 0.2 | AA4: ==IF(product!AA5<>"",product!AA5,"") -> 18 | AB4: ==IF(product!AB5<>"",product!AB5,"") -> 15 | AC4: ==IF(product!AC5<>"",product!AC5,"") -> 6 | AD4: ==IF('product'!AD5<>"", VLOOKUP('product'!AD5,product_attribute_14[#All],2,FALSE),"") -> 560 | AE4: ==IF(product!AE5<>"",product!AE5,"") -> DCBD-HWCC-001 | AF4: ==IF(product!AF5<>"",product!AF5,"") -> DCBD-HWCC-001 | AG4: ==IF(product!AG5<>"",product!AG5,"") -> https://cdn.cartup.com/product/2f33e0a9-85a1-41cf-9c96-530c9264408e.webp | AH4: ==IF(product!AH5<>"",product!AH5,"") -> 1 | AI4: ==IF(product!AI5<>"",product!AI5,"") -> 2280 | AJ4: ==IF(product!AJ5<>"",product!AJ5,"") -> 2130 | AK4: ==IF(product!AK5<>"",product!AK5,"") -> 46231 | AL4: ==IF(product!AL5<>"",product!AL5,"") -> 46596.999 | AM4: ==IF(product!AM5<>"",product!AM5,"")
A5: ==IF(product!A6<>"",product!A6,"") -> Hot Wheels Car Culture — Porsche 917K (Vintage Racing Club) | B5: ==IF(product!B6<>"",product!B6,"") -> Hot Wheels Car Culture — Porsche 917K ১:৬৪ ডাইকাস্ট মডেল কার (Vintage Racing Club) | C5: ==IF(product!C6<>"",product!C6,"") -> https://cdn.cartup.com/product/34a8c7fa-eef0-41c4-802d-112ed9316efd.webp | D5: ==IF(product!D6<>"",product!D6,"") | E5: ==IF(product!E6<>"",product!E6,"") | F5: ==IF(product!F6<>"",product!F6,"") | G5: ==IF(product!G6<>"",product!G6,"") | H5: ==IF(product!H6<>"",product!H6,"") | ... K5: ==IF(product!K6<>"",product!K6,"") | L5: ==IF('product'!L6<>"", VLOOKUP('product'!L6,product_attribute_1[#All],2,FALSE),"") -> 519 | M5: ==IF('product'!M6<>"", VLOOKUP('product'!M6,product_attribute_2[#All],2,FALSE),"") -> 2 | N5: ==IF(product!N6<>"",product!N6,"") -> car culture, porsche, 917k, le mans, vintage racing | O5: ==IF('product'!O6<>"", VLOOKUP('product'!O6,product_attribute_7[#All],2,FALSE),"") -> 392 | P5: ==IF('product'!P6<>"", VLOOKUP('product'!P6,product_attribute_6[#All],2,FALSE),"") -> 14776 | Q5: ==IF(product!Q6<>"",product!Q6,"") -> Car Culture premium series; Metal body & metal base; Real Riders rubber tyres | R5: ==IF(product!R6<>"",product!R6,"") -> Car Culture প্রিমিয়াম সিরিজ; মেটাল বডি ও মেটাল বেস; Real Riders রাবার টায়ার | S5: ==IF(product!S6<>"",product!S6,"") -> Le Mans-জয়ী Porsche 917K, তার আইকনিক #20 রেসিং লিভারিতে। প্রিমিয়াম Car Culture বিল্ড — মেটাল বডি, মেটাল বেস ও Real Riders রাবার টায়ার। স্কেল: 1:64 · প্রস্তুতকারক: Mattel · সিরিজ: Car Culture — Vintage Racing Club · মডেল নম্বর: FPY86 গঠন: Diecast metal body, metal base, Real Riders rubber tyres প্যাকেজিং: অরিজিনাল Hot Wheels প্রিমিয়াম ব্লিস্টার কার্ডে সিলড প্রস্তুতকারকের বয়সসীমা: ৩ বছর ও তদূর্ধ্ব (Mattel অফিসিয়াল)। ১০০% আসল — DiecastBD কর্তৃক আমদানিকৃত ও হাতে যাচাইকৃত। | T5: ==IF(product!T6<>"",product!T6,"") -> The Le Mans-winning Porsche 917K in its iconic #20 racing livery. Premium Car Culture build — metal/metal, Real Riders. Scale: 1:64 · Manufacturer: Mattel · Series: Car Culture — Vintage Racing Club · Model no: FPY86 Construction: Diecast metal body, metal base, Real Riders rubber tyres Packaging: sealed on the original Hot Wheels premium blister card Manufacturer age grade: 3 years and up (Mattel official). 100% authentic — imported and hand-verified by DiecastBD. | U5: ==IF(product!U6<>"",product!U6,"") -> 1 x Hot Wheels Car Culture — Porsche 917K (Vintage Racing Club), sealed on the original Hot Wheels premium blister card | V5: ==IF(product!V6<>"",product!V6,"") -> No manufacturer or seller warranty is offered on collectible diecast models. Every piece is supplied factory-sealed in its original packaging, is 100% authentic, and is hand-inspected before dispatch. Report any transit damage with the unopened parcel on delivery. | W5: ==IF(product!W6<>"",product!W6,"") -> কালেক্টিবল ডাইকাস্ট মডেলের ক্ষেত্রে কোনো ম্যানুফ্যাকচারার বা সেলার ওয়ারেন্টি দেওয়া হয় না। প্রতিটি পিস অরিজিনাল প্যাকেজিংয়ে ফ্যাক্টরি-সিলড অবস্থায় সরবরাহ করা হয়, ১০০% আসল, এবং পাঠানোর আগে হাতে যাচাই করা হয়। ডেলিভারির সময় পার্সেল না খুলে ট্রানজিটে কোনো ক্ষতি হয়ে থাকলে সঙ্গে সঙ্গে জানান। | X5: ==IF('product'!X6<>"", VLOOKUP('product'!X6,product_attribute_100[#All],2,FALSE),"") -> 3 | Y5: ==IF('product'!Y6<>"", VLOOKUP('product'!Y6,product_attribute_101[#All],2,FALSE),"") | Z5: ==IF(product!Z6<>"",product!Z6,"") -> 0.2 | AA5: ==IF(product!AA6<>"",product!AA6,"") -> 18 | AB5: ==IF(product!AB6<>"",product!AB6,"") -> 15 | AC5: ==IF(product!AC6<>"",product!AC6,"") -> 6 | AD5: ==IF('product'!AD6<>"", VLOOKUP('product'!AD6,product_attribute_14[#All],2,FALSE),"") -> 560 | AE5: ==IF(product!AE6<>"",product!AE6,"") -> DCBD-HWCC-002 | AF5: ==IF(product!AF6<>"",product!AF6,"") -> DCBD-HWCC-002 | AG5: ==IF(product!AG6<>"",product!AG6,"") -> https://cdn.cartup.com/product/34a8c7fa-eef0-41c4-802d-112ed9316efd.webp | AH5: ==IF(product!AH6<>"",product!AH6,"") -> 1 | AI5: ==IF(product!AI6<>"",product!AI6,"") -> 1860 | AJ5: ==IF(product!AJ6<>"",product!AJ6,"") -> 1740 | AK5: ==IF(product!AK6<>"",product!AK6,"") -> 46231 | AL5: ==IF(product!AL6<>"",product!AL6,"") -> 46596.999 | AM5: ==IF(product!AM6<>"",product!AM6,"")
A6: ==IF(product!A7<>"",product!A7,"") -> Hot Wheels Boulevard No.150 — Nissan Skyline GT-R R32 Pandem (HKS) | B6: ==IF(product!B7<>"",product!B7,"") -> Hot Wheels Boulevard No.150 — Nissan Skyline GT-R R32 Pandem (HKS) ১:৬৪ ডাইকাস্ট মডেল কার | C6: ==IF(product!C7<>"",product!C7,"") -> https://cdn.cartup.com/product/7c7d582e-685d-4fec-b5d9-cb277eea72e6.webp | D6: ==IF(product!D7<>"",product!D7,"") | E6: ==IF(product!E7<>"",product!E7,"") | F6: ==IF(product!F7<>"",product!F7,"") | G6: ==IF(product!G7<>"",product!G7,"") | H6: ==IF(product!H7<>"",product!H7,"") | ... K6: ==IF(product!K7<>"",product!K7,"") | L6: ==IF('product'!L7<>"", VLOOKUP('product'!L7,product_attribute_1[#All],2,FALSE),"") -> 519 | M6: ==IF('product'!M7<>"", VLOOKUP('product'!M7,product_attribute_2[#All],2,FALSE),"") -> 2 | N6: ==IF(product!N7<>"",product!N7,"") -> jdm, nissan, skyline, r32, gt-r, pandem, hks, boulevard, godzilla | O6: ==IF('product'!O7<>"", VLOOKUP('product'!O7,product_attribute_7[#All],2,FALSE),"") -> 392 | P6: ==IF('product'!P7<>"", VLOOKUP('product'!P7,product_attribute_6[#All],2,FALSE),"") -> 14776 | Q6: ==IF(product!Q7<>"",product!Q7,"") -> Boulevard premium series; Pandem widebody kit; HKS racing livery; Real Riders rubber tyres | R6: ==IF(product!R7<>"",product!R7,"") -> Boulevard প্রিমিয়াম সিরিজ; Pandem ওয়াইডবডি কিট; HKS রেসিং লিভারি; Real Riders রাবার টায়ার | S6: ==IF(product!S7<>"",product!S7,"") -> Godzilla — সম্পূর্ণ Pandem ওয়াইডবডি এবং কিংবদন্তি HKS রঙে। Boulevard প্রিমিয়াম — মেটাল বেস, Real Riders রাবার টায়ার। এ বছরের সবচেয়ে চাহিদাসম্পন্ন R32 কাস্টিংগুলোর একটি। স্কেল: 1:64 · প্রস্তুতকারক: Mattel · সিরিজ: Boulevard #150 · মডেল নম্বর: GJT68 গঠন: Diecast metal body, metal base, Real Riders rubber tyres প্যাকেজিং: অরিজিনাল Hot Wheels প্রিমিয়াম ব্লিস্টার কার্ডে সিলড প্রস্তুতকারকের বয়সসীমা: ৩ বছর ও তদূর্ধ্ব (Mattel অফিসিয়াল)। ১০০% আসল — DiecastBD কর্তৃক আমদানিকৃত ও হাতে যাচাইকৃত। | T6: ==IF(product!T7<>"",product!T7,"") -> Godzilla in full Pandem widebody and legendary HKS colours. Boulevard premium — metal base, Real Riders. One of the most wanted R32 castings of the year. Scale: 1:64 · Manufacturer: Mattel · Series: Boulevard #150 · Model no: GJT68 Construction: Diecast metal body, metal base, Real Riders rubber tyres Packaging: sealed on the original Hot Wheels premium blister card Manufacturer age grade: 3 years and up (Mattel official). 100% authentic — imported and hand-verified by DiecastBD. | U6: ==IF(product!U7<>"",product!U7,"") -> 1 x Hot Wheels Boulevard No.150 — Nissan Skyline GT-R R32 Pandem (HKS), sealed on the original Hot Wheels premium blister card | V6: ==IF(product!V7<>"",product!V7,"") -> No manufacturer or seller warranty is offered on collectible diecast models. Every piece is supplied factory-sealed in its original packaging, is 100% authentic, and is hand-inspected before dispatch. Report any transit damage with the unopened parcel on delivery. | W6: ==IF(product!W7<>"",product!W7,"") -> কালেক্টিবল ডাইকাস্ট মডেলের ক্ষেত্রে কোনো ম্যানুফ্যাকচারার বা সেলার ওয়ারেন্টি দেওয়া হয় না। প্রতিটি পিস অরিজিনাল প্যাকেজিংয়ে ফ্যাক্টরি-সিলড অবস্থায় সরবরাহ করা হয়, ১০০% আসল, এবং পাঠানোর আগে হাতে যাচাই করা হয়। ডেলিভারির সময় পার্সেল না খুলে ট্রানজিটে কোনো ক্ষতি হয়ে থাকলে সঙ্গে সঙ্গে জানান। | X6: ==IF('product'!X7<>"", VLOOKUP('product'!X7,product_attribute_100[#All],2,FALSE),"") -> 3 | Y6: ==IF('product'!Y7<>"", VLOOKUP('product'!Y7,product_attribute_101[#All],2,FALSE),"") | Z6: ==IF(product!Z7<>"",product!Z7,"") -> 0.2 | AA6: ==IF(product!AA7<>"",product!AA7,"") -> 18 | AB6: ==IF(product!AB7<>"",product!AB7,"") -> 15 | AC6: ==IF(product!AC7<>"",product!AC7,"") -> 6 | AD6: ==IF('product'!AD7<>"", VLOOKUP('product'!AD7,product_attribute_14[#All],2,FALSE),"") -> 562 | AE6: ==IF(product!AE7<>"",product!AE7,"") -> DCBD-HWCC-003 | AF6: ==IF(product!AF7<>"",product!AF7,"") -> DCBD-HWCC-003 | AG6: ==IF(product!AG7<>"",product!AG7,"") -> https://cdn.cartup.com/product/7c7d582e-685d-4fec-b5d9-cb277eea72e6.webp | AH6: ==IF(product!AH7<>"",product!AH7,"") -> 2 | AI6: ==IF(product!AI7<>"",product!AI7,"") -> 1980 | AJ6: ==IF(product!AJ7<>"",product!AJ7,"") -> 1850 | AK6: ==IF(product!AK7<>"",product!AK7,"") -> 46231 | AL6: ==IF(product!AL7<>"",product!AL7,"") -> 46596.999 | AM6: ==IF(product!AM7<>"",product!AM7,"")
A7: ==IF(product!A8<>"",product!A8,"") -> Hot Wheels Car Culture — BMW M3 E46 (Power Trip) | B7: ==IF(product!B8<>"",product!B8,"") -> Hot Wheels Car Culture — BMW M3 E46 ১:৬৪ ডাইকাস্ট মডেল কার (Power Trip) | C7: ==IF(product!C8<>"",product!C8,"") -> https://cdn.cartup.com/product/8f1fb6dd-75ff-4e14-9de3-90d1cfcdd56d.webp | D7: ==IF(product!D8<>"",product!D8,"") | E7: ==IF(product!E8<>"",product!E8,"") | F7: ==IF(product!F8<>"",product!F8,"") | G7: ==IF(product!G8<>"",product!G8,"") | H7: ==IF(product!H8<>"",product!H8,"") | ... K7: ==IF(product!K8<>"",product!K8,"") | L7: ==IF('product'!L8<>"", VLOOKUP('product'!L8,product_attribute_1[#All],2,FALSE),"") -> 519 | M7: ==IF('product'!M8<>"", VLOOKUP('product'!M8,product_attribute_2[#All],2,FALSE),"") -> 2 | N7: ==IF(product!N8<>"",product!N8,"") -> car culture, bmw, m3, e46, power trip | O7: ==IF('product'!O8<>"", VLOOKUP('product'!O8,product_attribute_7[#All],2,FALSE),"") -> 392 | P7: ==IF('product'!P8<>"", VLOOKUP('product'!P8,product_attribute_6[#All],2,FALSE),"") -> 14776 | Q7: ==IF(product!Q8<>"",product!Q8,"") -> Car Culture premium series; Metal body & metal base; Real Riders rubber tyres | R7: ==IF(product!R8<>"",product!R8,"") -> Car Culture প্রিমিয়াম সিরিজ; মেটাল বডি ও মেটাল বেস; Real Riders রাবার টায়ার | S7: ==IF(product!S8<>"",product!S8,"") -> E46 M3 — গাড়িপ্রেমীদের BMW — গাঢ় সবুজ রঙে, প্রিমিয়াম Power Trip কার্ডে। মেটাল বডি ও মেটাল বেস, সঙ্গে Real Riders রাবার টায়ার। স্কেল: 1:64 · প্রস্তুতকারক: Mattel · সিরিজ: Car Culture — Power Trip · মডেল নম্বর: FPY86 গঠন: Diecast metal body, metal base, Real Riders rubber tyres প্যাকেজিং: অরিজিনাল Hot Wheels প্রিমিয়াম ব্লিস্টার কার্ডে সিলড প্রস্তুতকারকের বয়সসীমা: ৩ বছর ও তদূর্ধ্ব (Mattel অফিসিয়াল)। ১০০% আসল — DiecastBD কর্তৃক আমদানিকৃত ও হাতে যাচাইকৃত। | T7: ==IF(product!T8<>"",product!T8,"") -> The E46 M3 — the enthusiast's BMW — in deep green on a premium Power Trip card. Metal/metal with Real Riders. Scale: 1:64 · Manufacturer: Mattel · Series: Car Culture — Power Trip · Model no: FPY86 Construction: Diecast metal body, metal base, Real Riders rubber tyres Packaging: sealed on the original Hot Wheels premium blister card Manufacturer age grade: 3 years and up (Mattel official). 100% authentic — imported and hand-verified by DiecastBD. | U7: ==IF(product!U8<>"",product!U8,"") -> 1 x Hot Wheels Car Culture — BMW M3 E46 (Power Trip), sealed on the original Hot Wheels premium blister card | V7: ==IF(product!V8<>"",product!V8,"") -> No manufacturer or seller warranty is offered on collectible diecast models. Every piece is supplied factory-sealed in its original packaging, is 100% authentic, and is hand-inspected before dispatch. Report any transit damage with the unopened parcel on delivery. | W7: ==IF(product!W8<>"",product!W8,"") -> কালেক্টিবল ডাইকাস্ট মডেলের ক্ষেত্রে কোনো ম্যানুফ্যাকচারার বা সেলার ওয়ারেন্টি দেওয়া হয় না। প্রতিটি পিস অরিজিনাল প্যাকেজিংয়ে ফ্যাক্টরি-সিলড অবস্থায় সরবরাহ করা হয়, ১০০% আসল, এবং পাঠানোর আগে হাতে যাচাই করা হয়। ডেলিভারির সময় পার্সেল না খুলে ট্রানজিটে কোনো ক্ষতি হয়ে থাকলে সঙ্গে সঙ্গে জানান। | X7: ==IF('product'!X8<>"", VLOOKUP('product'!X8,product_attribute_100[#All],2,FALSE),"") -> 3 | Y7: ==IF('product'!Y8<>"", VLOOKUP('product'!Y8,product_attribute_101[#All],2,FALSE),"") | Z7: ==IF(product!Z8<>"",product!Z8,"") -> 0.2 | AA7: ==IF(product!AA8<>"",product!AA8,"") -> 18 | AB7: ==IF(product!AB8<>"",product!AB8,"") -> 15 | AC7: ==IF(product!AC8<>"",product!AC8,"") -> 6 | AD7: ==IF('product'!AD8<>"", VLOOKUP('product'!AD8,product_attribute_14[#All],2,FALSE),"") -> 592 | AE7: ==IF(product!AE8<>"",product!AE8,"") -> DCBD-HWCC-004 | AF7: ==IF(product!AF8<>"",product!AF8,"") -> DCBD-HWCC-004 | AG7: ==IF(product!AG8<>"",product!AG8,"") -> https://cdn.cartup.com/product/8f1fb6dd-75ff-4e14-9de3-90d1cfcdd56d.webp | AH7: ==IF(product!AH8<>"",product!AH8,"") -> 1 | AI7: ==IF(product!AI8<>"",product!AI8,"") -> 2070 | AJ7: ==IF(product!AJ8<>"",product!AJ8,"") -> 1930 | AK7: ==IF(product!AK8<>"",product!AK8,"") -> 46231 | AL7: ==IF(product!AL8<>"",product!AL8,"") -> 46596.999 | AM7: ==IF(product!AM8<>"",product!AM8,"")
A8: ==IF(product!A9<>"",product!A9,"") -> Hot Wheels Car Culture — Nissan Skyline GT-R R32 Pandem, Yellow (Ronin Run II) | B8: ==IF(product!B9<>"",product!B9,"") -> Hot Wheels Car Culture — Nissan Skyline GT-R R32 Pandem হলুদ ১:৬৪ ডাইকাস্ট মডেল কার (Ronin Run II) | C8: ==IF(product!C9<>"",product!C9,"") -> https://cdn.cartup.com/product/a47f07ca-58c7-4173-8a36-14f9b3a2a61b.webp | D8: ==IF(product!D9<>"",product!D9,"") | E8: ==IF(product!E9<>"",product!E9,"") | F8: ==IF(product!F9<>"",product!F9,"") | G8: ==IF(product!G9<>"",product!G9,"") | H8: ==IF(product!H9<>"",product!H9,"") | ... K8: ==IF(product!K9<>"",product!K9,"") | L8: ==IF('product'!L9<>"", VLOOKUP('product'!L9,product_attribute_1[#All],2,FALSE),"") -> 519 | M8: ==IF('product'!M9<>"", VLOOKUP('product'!M9,product_attribute_2[#All],2,FALSE),"") -> 2 | N8: ==IF(product!N9<>"",product!N9,"") -> jdm, nissan, skyline, r32, gt-r, pandem, ronin run, godzilla | O8: ==IF('product'!O9<>"", VLOOKUP('product'!O9,product_attribute_7[#All],2,FALSE),"") -> 392 | P8: ==IF('product'!P9<>"", VLOOKUP('product'!P9,product_attribute_6[#All],2,FALSE),"") -> 14776 | Q8: ==IF(product!Q9<>"",product!Q9,"") -> Car Culture premium series; Pandem widebody kit; Real Riders rubber tyres | R8: ==IF(product!R9<>"",product!R9,"") -> Car Culture প্রিমিয়াম সিরিজ; Pandem ওয়াইডবডি কিট; Real Riders রাবার টায়ার | S8: ==IF(product!S9<>"",product!S9,"") -> Ronin Run II সিরিজের Pandem-কিট R32 GT-R, উজ্জ্বল হলুদ রঙে। প্রিমিয়াম মেটাল বেস এবং Real Riders রাবার টায়ার। স্কেল: 1:64 · প্রস্তুতকারক: Mattel · সিরিজ: Car Culture — Ronin Run II · মডেল নম্বর: FPY86 গঠন: Diecast metal body, metal base, Real Riders rubber tyres প্যাকেজিং: অরিজিনাল Hot Wheels প্রিমিয়াম ব্লিস্টার কার্ডে সিলড প্রস্তুতকারকের বয়সসীমা: ৩ বছর ও তদূর্ধ্ব (Mattel অফিসিয়াল)। ১০০% আসল — DiecastBD কর্তৃক আমদানিকৃত ও হাতে যাচাইকৃত। | T8: ==IF(product!T9<>"",product!T9,"") -> Pandem-kitted R32 GT-R in bold yellow from the Ronin Run II series. Premium metal base and Real Riders. Scale: 1:64 · Manufacturer: Mattel · Series: Car Culture — Ronin Run II · Model no: FPY86 Construction: Diecast metal body, metal base, Real Riders rubber tyres Packaging: sealed on the original Hot Wheels premium blister card Manufacturer age grade: 3 years and up (Mattel official). 100% authentic — imported and hand-verified by DiecastBD. | U8: ==IF(product!U9<>"",product!U9,"") -> 1 x Hot Wheels Car Culture — Nissan Skyline GT-R R32 Pandem, Yellow (Ronin Run II), sealed on the original Hot Wheels premium blister card | V8: ==IF(product!V9<>"",product!V9,"") -> No manufacturer or seller warranty is offered on collectible diecast models. Every piece is supplied factory-sealed in its original packaging, is 100% authentic, and is hand-inspected before dispatch. Report any transit damage with the unopened parcel on delivery. | W8: ==IF(product!W9<>"",product!W9,"") -> কালেক্টিবল ডাইকাস্ট মডেলের ক্ষেত্রে কোনো ম্যানুফ্যাকচারার বা সেলার ওয়ারেন্টি দেওয়া হয় না। প্রতিটি পিস অরিজিনাল প্যাকেজিংয়ে ফ্যাক্টরি-সিলড অবস্থায় সরবরাহ করা হয়, ১০০% আসল, এবং পাঠানোর আগে হাতে যাচাই করা হয়। ডেলিভারির সময় পার্সেল না খুলে ট্রানজিটে কোনো ক্ষতি হয়ে থাকলে সঙ্গে সঙ্গে জানান। | X8: ==IF('product'!X9<>"", VLOOKUP('product'!X9,product_attribute_100[#All],2,FALSE),"") -> 3 | Y8: ==IF('product'!Y9<>"", VLOOKUP('product'!Y9,product_attribute_101[#All],2,FALSE),"") | Z8: ==IF(product!Z9<>"",product!Z9,"") -> 0.2 | AA8: ==IF(product!AA9<>"",product!AA9,"") -> 18 | AB8: ==IF(product!AB9<>"",product!AB9,"") -> 15 | AC8: ==IF(product!AC9<>"",product!AC9,"") -> 6 | AD8: ==IF('product'!AD9<>"", VLOOKUP('product'!AD9,product_attribute_14[#All],2,FALSE),"") -> 576 | AE8: ==IF(product!AE9<>"",product!AE9,"") -> DCBD-HWCC-005 | AF8: ==IF(product!AF9<>"",product!AF9,"") -> DCBD-HWCC-005 | AG8: ==IF(product!AG9<>"",product!AG9,"") -> https://cdn.cartup.com/product/a47f07ca-58c7-4173-8a36-14f9b3a2a61b.webp | AH8: ==IF(product!AH9<>"",product!AH9,"") -> 1 | AI8: ==IF(product!AI9<>"",product!AI9,"") -> 1670 | AJ8: ==IF(product!AJ9<>"",product!AJ9,"") -> 1560 | AK8: ==IF(product!AK9<>"",product!AK9,"") -> 46231 | AL8: ==IF(product!AL9<>"",product!AL9,"") -> 46596.999 | AM8: ==IF(product!AM9<>"",product!AM9,"")
A9: ==IF(product!A10<>"",product!A10,"") -> Hot Wheels Car Culture — Mad Mike Mazda RX-3 Wagon + Trailer (Ronin Run II) | B9: ==IF(product!B10<>"",product!B10,"") -> Hot Wheels Car Culture — Mad Mike Mazda RX-3 Wagon + Trailer ১:৬৪ ডাইকাস্ট মডেল কার (Ronin Run II) | C9: ==IF(product!C10<>"",product!C10,"") -> https://cdn.cartup.com/product/bc3d35a6-d010-425e-a8e6-e656fa566d50.webp | D9: ==IF(product!D10<>"",product!D10,"") | E9: ==IF(product!E10<>"",product!E10,"") | F9: ==IF(product!F10<>"",product!F10,"") | G9: ==IF(product!G10<>"",product!G10,"") | H9: ==IF(product!H10<>"",product!H10,"") | ... K9: ==IF(product!K10<>"",product!K10,"") | L9: ==IF('product'!L10<>"", VLOOKUP('product'!L10,product_attribute_1[#All],2,FALSE),"") -> 519 | M9: ==IF('product'!M10<>"", VLOOKUP('product'!M10,product_attribute_2[#All],2,FALSE),"") -> 2 | N9: ==IF(product!N10<>"",product!N10,"") -> jdm, mazda, rx-3, mad mike, rotary, ronin run, bd exclusive | O9: ==IF('product'!O10<>"", VLOOKUP('product'!O10,product_attribute_7[#All],2,FALSE),"") -> 392 | P9: ==IF('product'!P10<>"", VLOOKUP('product'!P10,product_attribute_6[#All],2,FALSE),"") -> 14776 | Q9: ==IF(product!Q10<>"",product!Q10,"") -> Car Culture premium series; Includes matching trailer; Toyo Tires livery; Real Riders rubber tyres | R9: ==IF(product!R10<>"",product!R10,"") -> Car Culture প্রিমিয়াম সিরিজ; সঙ্গে ম্যাচিং ট্রেইলার; Toyo Tires লিভারি; Real Riders রাবার টায়ার | S9: ==IF(product!S10<>"",product!S10,"") -> Mad Mike-এর রোটারি Mazda RX-3 ওয়াগন, সঙ্গে ম্যাচিং ট্রেইলার পিস — একটি প্রিমিয়াম কার্ডে দুটি মডেল। স্কেল: 1:64 · প্রস্তুতকারক: Mattel · সিরিজ: Car Culture — Ronin Run II · মডেল নম্বর: FPY86 গঠন: Diecast metal body, metal base, Real Riders rubber tyres প্যাকেজিং: অরিজিনাল Hot Wheels প্রিমিয়াম ব্লিস্টার কার্ডে সিলড প্রস্তুতকারকের বয়সসীমা: ৩ বছর ও তদূর্ধ্ব (Mattel অফিসিয়াল)। ১০০% আসল — DiecastBD কর্তৃক আমদানিকৃত ও হাতে যাচাইকৃত। | T9: ==IF(product!T10<>"",product!T10,"") -> Mad Mike's rotary Mazda RX-3 wagon complete with a matching trailer piece — two models on one premium card. Scale: 1:64 · Manufacturer: Mattel · Series: Car Culture — Ronin Run II · Model no: FPY86 Construction: Diecast metal body, metal base, Real Riders rubber tyres Packaging: sealed on the original Hot Wheels premium blister card Manufacturer age grade: 3 years and up (Mattel official). 100% authentic — imported and hand-verified by DiecastBD. | U9: ==IF(product!U10<>"",product!U10,"") -> 1 x Hot Wheels Car Culture — Mad Mike Mazda RX-3 Wagon + Trailer (Ronin Run II), sealed on the original Hot Wheels premium blister card | V9: ==IF(product!V10<>"",product!V10,"") -> No manufacturer or seller warranty is offered on collectible diecast models. Every piece is supplied factory-sealed in its original packaging, is 100% authentic, and is hand-inspected before dispatch. Report any transit damage with the unopened parcel on delivery. | W9: ==IF(product!W10<>"",product!W10,"") -> কালেক্টিবল ডাইকাস্ট মডেলের ক্ষেত্রে কোনো ম্যানুফ্যাকচারার বা সেলার ওয়ারেন্টি দেওয়া হয় না। প্রতিটি পিস অরিজিনাল প্যাকেজিংয়ে ফ্যাক্টরি-সিলড অবস্থায় সরবরাহ করা হয়, ১০০% আসল, এবং পাঠানোর আগে হাতে যাচাই করা হয়। ডেলিভারির সময় পার্সেল না খুলে ট্রানজিটে কোনো ক্ষতি হয়ে থাকলে সঙ্গে সঙ্গে জানান। | X9: ==IF('product'!X10<>"", VLOOKUP('product'!X10,product_attribute_100[#All],2,FALSE),"") -> 3 | Y9: ==IF('product'!Y10<>"", VLOOKUP('product'!Y10,product_attribute_101[#All],2,FALSE),"") | Z9: ==IF(product!Z10<>"",product!Z10,"") -> 0.2 | AA9: ==IF(product!AA10<>"",product!AA10,"") -> 18 | AB9: ==IF(product!AB10<>"",product!AB10,"") -> 15 | AC9: ==IF(product!AC10<>"",product!AC10,"") -> 6 | AD9: ==IF('product'!AD10<>"", VLOOKUP('product'!AD10,product_attribute_14[#All],2,FALSE),"") -> 562 | AE9: ==IF(product!AE10<>"",product!AE10,"") -> DCBD-HWCC-006 | AF9: ==IF(product!AF10<>"",product!AF10,"") -> DCBD-HWCC-006 | AG9: ==IF(product!AG10<>"",product!AG10,"") -> https://cdn.cartup.com/product/bc3d35a6-d010-425e-a8e6-e656fa566d50.webp | AH9: ==IF(product!AH10<>"",product!AH10,"") -> 2 | AI9: ==IF(product!AI10<>"",product!AI10,"") -> 1950 | AJ9: ==IF(product!AJ10<>"",product!AJ10,"") -> 1820 | AK9: ==IF(product!AK10<>"",product!AK10,"") -> 46231 | AL9: ==IF(product!AL10<>"",product!AL10,"") -> 46596.999 | AM9: ==IF(product!AM10<>"",product!AM10,"")
A10: ==IF(product!A11<>"",product!A11,"") -> Hot Wheels Car Culture — Ferrari Testarossa (Modern Classics, 10th Anniversary) | B10: ==IF(product!B11<>"",product!B11,"") -> Hot Wheels Car Culture — Ferrari Testarossa ১:৬৪ ডাইকাস্ট মডেল কার (Modern Classics, 10th Anniversary) | C10: ==IF(product!C11<>"",product!C11,"") -> https://cdn.cartup.com/product/fc485c81-2772-43d6-8958-17eaf7727768.webp | D10: ==IF(product!D11<>"",product!D11,"") | E10: ==IF(product!E11<>"",product!E11,"") | F10: ==IF(product!F11<>"",product!F11,"") | G10: ==IF(product!G11<>"",product!G11,"") | H10: ==IF(product!H11<>"",product!H11,"") | ... K10: ==IF(product!K11<>"",product!K11,"") | L10: ==IF('product'!L11<>"", VLOOKUP('product'!L11,product_attribute_1[#All],2,FALSE),"") -> 519 | M10: ==IF('product'!M11<>"", VLOOKUP('product'!M11,product_attribute_2[#All],2,FALSE),"") -> 2 | N10: ==IF(product!N11<>"",product!N11,"") -> car culture, ferrari, testarossa, modern classics, 80s | O10: ==IF('product'!O11<>"", VLOOKUP('product'!O11,product_attribute_7[#All],2,FALSE),"") -> 392 | P10: ==IF('product'!P11<>"", VLOOKUP('product'!P11,product_attribute_6[#All],2,FALSE),"") -> 14776 | Q10: ==IF(product!Q11<>"",product!Q11,"") -> Car Culture 10th Anniversary; Metal body & metal base; Real Riders rubber tyres | R10: ==IF(product!R11<>"",product!R11,"") -> Car Culture ১০ম বার্ষিকী সংস্করণ; মেটাল বডি ও মেটাল বেস; Real Riders রাবার টায়ার | S10: ==IF(product!S11<>"",product!S11,"") -> আশির দশকের পোস্টার কার — Ferrari Testarossa, তার চিরচেনা লাল রঙে, Car Culture-এর ১০ম বার্ষিকী কার্ডে। মেটাল বডি ও মেটাল বেস, Real Riders রাবার টায়ার। স্কেল: 1:64 · প্রস্তুতকারক: Mattel · সিরিজ: Car Culture — Modern Classics (10th Anniversary) · মডেল নম্বর: FPY86 গঠন: Diecast metal body, metal base, Real Riders rubber tyres প্যাকেজিং: অরিজিনাল Hot Wheels প্রিমিয়াম ব্লিস্টার কার্ডে সিলড প্রস্তুতকারকের বয়সসীমা: ৩ বছর ও তদূর্ধ্ব (Mattel অফিসিয়াল)। ১০০% আসল — DiecastBD কর্তৃক আমদানিকৃত ও হাতে যাচাইকৃত। | T10: ==IF(product!T11<>"",product!T11,"") -> The 80s poster car — Ferrari Testarossa in signature red on the Car Culture 10th-anniversary card. Metal/metal, Real Riders. Scale: 1:64 · Manufacturer: Mattel · Series: Car Culture — Modern Classics (10th Anniversary) · Model no: FPY86 Construction: Diecast metal body, metal base, Real Riders rubber tyres Packaging: sealed on the original Hot Wheels premium blister card Manufacturer age grade: 3 years and up (Mattel official). 100% authentic — imported and hand-verified by DiecastBD. | U10: ==IF(product!U11<>"",product!U11,"") -> 1 x Hot Wheels Car Culture — Ferrari Testarossa (Modern Classics, 10th Anniversary), sealed on the original Hot Wheels premium blister card | V10: ==IF(product!V11<>"",product!V11,"") -> No manufacturer or seller warranty is offered on collectible diecast models. Every piece is supplied factory-sealed in its original packaging, is 100% authentic, and is hand-inspected before dispatch. Report any transit damage with the unopened parcel on delivery. | W10: ==IF(product!W11<>"",product!W11,"") -> কালেক্টিবল ডাইকাস্ট মডেলের ক্ষেত্রে কোনো ম্যানুফ্যাকচারার বা সেলার ওয়ারেন্টি দেওয়া হয় না। প্রতিটি পিস অরিজিনাল প্যাকেজিংয়ে ফ্যাক্টরি-সিলড অবস্থায় সরবরাহ করা হয়, ১০০% আসল, এবং পাঠানোর আগে হাতে যাচাই করা হয়। ডেলিভারির সময় পার্সেল না খুলে ট্রানজিটে কোনো ক্ষতি হয়ে থাকলে সঙ্গে সঙ্গে জানান। | X10: ==IF('product'!X11<>"", VLOOKUP('product'!X11,product_attribute_100[#All],2,FALSE),"") -> 3 | Y10: ==IF('product'!Y11<>"", VLOOKUP('product'!Y11,product_attribute_101[#All],2,FALSE),"") | Z10: ==IF(product!Z11<>"",product!Z11,"") -> 0.2 | AA10: ==IF(product!AA11<>"",product!AA11,"") -> 18 | AB10: ==IF(product!AB11<>"",product!AB11,"") -> 15 | AC10: ==IF(product!AC11<>"",product!AC11,"") -> 6 | AD10: ==IF('product'!AD11<>"", VLOOKUP('product'!AD11,product_attribute_14[#All],2,FALSE),"") -> 561 | AE10: ==IF(product!AE11<>"",product!AE11,"") -> DCBD-HWCC-007 | AF10: ==IF(product!AF11<>"",product!AF11,"") -> DCBD-HWCC-007 | AG10: ==IF(product!AG11<>"",product!AG11,"") -> https://cdn.cartup.com/product/fc485c81-2772-43d6-8958-17eaf7727768.webp | AH10: ==IF(product!AH11<>"",product!AH11,"") -> 2 | AI10: ==IF(product!AI11<>"",product!AI11,"") -> 2300 | AJ10: ==IF(product!AJ11<>"",product!AJ11,"") -> 2150 | AK10: ==IF(product!AK11<>"",product!AK11,"") -> 46231 | AL10: ==IF(product!AL11<>"",product!AL11,"") -> 46596.999 | AM10: ==IF(product!AM11<>"",product!AM11,"")
A11: ==IF(product!A12<>"",product!A12,"") -> Hot Wheels Car Culture — Nissan Skyline 2000GT-R LBWK (Japan Historics) | B11: ==IF(product!B12<>"",product!B12,"") -> Hot Wheels Car Culture — Nissan Skyline 2000GT-R LBWK ১:৬৪ ডাইকাস্ট মডেল কার (Japan Historics) | C11: ==IF(product!C12<>"",product!C12,"") -> https://cdn.cartup.com/product/480da80f-7c29-4561-a908-4581f0f8841b.webp | D11: ==IF(product!D12<>"",product!D12,"") | E11: ==IF(product!E12<>"",product!E12,"") | F11: ==IF(product!F12<>"",product!F12,"") | G11: ==IF(product!G12<>"",product!G12,"") | H11: ==IF(product!H12<>"",product!H12,"") | ... K11: ==IF(product!K12<>"",product!K12,"") | L11: ==IF('product'!L12<>"", VLOOKUP('product'!L12,product_attribute_1[#All],2,FALSE),"") -> 519 | M11: ==IF('product'!M12<>"", VLOOKUP('product'!M12,product_attribute_2[#All],2,FALSE),"") -> 2 | N11: ==IF(product!N12<>"",product!N12,"") -> jdm, nissan, skyline, hakosuka, lbwk, liberty walk, gold label | O11: ==IF('product'!O12<>"", VLOOKUP('product'!O12,product_attribute_7[#All],2,FALSE),"") -> 392 | P11: ==IF('product'!P12<>"", VLOOKUP('product'!P12,product_attribute_6[#All],2,FALSE),"") -> 14776 | Q11: ==IF(product!Q12<>"",product!Q12,"") -> Gold Label premium series; Liberty Walk widebody; Real Riders rubber tyres | R11: ==IF(product!R12<>"",product!R12,"") -> Gold Label প্রিমিয়াম সিরিজ; Liberty Walk ওয়াইডবডি; Real Riders রাবার টায়ার | S11: ==IF(product!S12<>"",product!S12,"") -> Hakosuka Skyline 2000GT-R, Liberty Walk ওয়াইডবডি সহ — পুরোনো দিনের JDM-এর সঙ্গে আধুনিক টিউনার কালচারের মিলন। প্রিমিয়াম গোল্ড-লেবেল বিল্ড। স্কেল: 1:64 · প্রস্তুতকারক: Mattel · সিরিজ: Car Culture — Japan Historics 5 (Gold Label) · মডেল নম্বর: FPY86 গঠন: Diecast metal body, metal base, Real Riders rubber tyres প্যাকেজিং: অরিজিনাল Hot Wheels প্রিমিয়াম ব্লিস্টার কার্ডে সিলড প্রস্তুতকারকের বয়সসীমা: ৩ বছর ও তদূর্ধ্ব (Mattel অফিসিয়াল)। ১০০% আসল — DiecastBD কর্তৃক আমদানিকৃত ও হাতে যাচাইকৃত। | T11: ==IF(product!T12<>"",product!T12,"") -> Hakosuka Skyline 2000GT-R wearing a Liberty Walk widebody — vintage JDM meets modern tuner culture. Premium gold-label build. Scale: 1:64 · Manufacturer: Mattel · Series: Car Culture — Japan Historics 5 (Gold Label) · Model no: FPY86 Construction: Diecast metal body, metal base, Real Riders rubber tyres Packaging: sealed on the original Hot Wheels premium blister card Manufacturer age grade: 3 years and up (Mattel official). 100% authentic — imported and hand-verified by DiecastBD. | U11: ==IF(product!U12<>"",product!U12,"") -> 1 x Hot Wheels Car Culture — Nissan Skyline 2000GT-R LBWK (Japan Historics), sealed on the original Hot Wheels premium blister card | V11: ==IF(product!V12<>"",product!V12,"") -> No manufacturer or seller warranty is offered on collectible diecast models. Every piece is supplied factory-sealed in its original packaging, is 100% authentic, and is hand-inspected before dispatch. Report any transit damage with the unopened parcel on delivery. | W11: ==IF(product!W12<>"",product!W12,"") -> কালেক্টিবল ডাইকাস্ট মডেলের ক্ষেত্রে কোনো ম্যানুফ্যাকচারার বা সেলার ওয়ারেন্টি দেওয়া হয় না। প্রতিটি পিস অরিজিনাল প্যাকেজিংয়ে ফ্যাক্টরি-সিলড অবস্থায় সরবরাহ করা হয়, ১০০% আসল, এবং পাঠানোর আগে হাতে যাচাই করা হয়। ডেলিভারির সময় পার্সেল না খুলে ট্রানজিটে কোনো ক্ষতি হয়ে থাকলে সঙ্গে সঙ্গে জানান। | X11: ==IF('product'!X12<>"", VLOOKUP('product'!X12,product_attribute_100[#All],2,FALSE),"") -> 3 | Y11: ==IF('product'!Y12<>"", VLOOKUP('product'!Y12,product_attribute_101[#All],2,FALSE),"") | Z11: ==IF(product!Z12<>"",product!Z12,"") -> 0.2 | AA11: ==IF(product!AA12<>"",product!AA12,"") -> 18 | AB11: ==IF(product!AB12<>"",product!AB12,"") -> 15 | AC11: ==IF(product!AC12<>"",product!AC12,"") -> 6 | AD11: ==IF('product'!AD12<>"", VLOOKUP('product'!AD12,product_attribute_14[#All],2,FALSE),"") -> 963 | AE11: ==IF(product!AE12<>"",product!AE12,"") -> DCBD-HWCC-008 | AF11: ==IF(product!AF12<>"",product!AF12,"") -> DCBD-HWCC-008 | AG11: ==IF(product!AG12<>"",product!AG12,"") -> https://cdn.cartup.com/product/480da80f-7c29-4561-a908-4581f0f8841b.webp | AH11: ==IF(product!AH12<>"",product!AH12,"") -> 1 | AI11: ==IF(product!AI12<>"",product!AI12,"") -> 1890 | AJ11: ==IF(product!AJ12<>"",product!AJ12,"") -> 1770 | AK11: ==IF(product!AK12<>"",product!AK12,"") -> 46231 | AL11: ==IF(product!AL12<>"",product!AL12,"") -> 46596.999 | AM11: ==IF(product!AM12<>"",product!AM12,"")
A12: ==IF(product!A13<>"",product!A13,"") -> Hot Wheels Car Culture — LB-Kaido Works Nissan Skyline GT-R R32 (Aero Styles) | B12: ==IF(product!B13<>"",product!B13,"") -> Hot Wheels Car Culture — LB-Kaido Works Nissan Skyline GT-R R32 ১:৬৪ ডাইকাস্ট মডেল কার (Aero Styles) | C12: ==IF(product!C13<>"",product!C13,"") -> https://cdn.cartup.com/product/375e5a3e-b231-4b51-97b0-619fba461cc6.webp | D12: ==IF(product!D13<>"",product!D13,"") | E12: ==IF(product!E13<>"",product!E13,"") | F12: ==IF(product!F13<>"",product!F13,"") | G12: ==IF(product!G13<>"",product!G13,"") | H12: ==IF(product!H13<>"",product!H13,"") | ... K12: ==IF(product!K13<>"",product!K13,"") | L12: ==IF('product'!L13<>"", VLOOKUP('product'!L13,product_attribute_1[#All],2,FALSE),"") -> 519 | M12: ==IF('product'!M13<>"", VLOOKUP('product'!M13,product_attribute_2[#All],2,FALSE),"") -> 2 | N12: ==IF(product!N13<>"",product!N13,"") -> jdm, nissan, skyline, r32, gt-r, lbwk, kaido works, aero styles, godzilla | O12: ==IF('product'!O13<>"", VLOOKUP('product'!O13,product_attribute_7[#All],2,FALSE),"") -> 392 | P12: ==IF('product'!P13<>"", VLOOKUP('product'!P13,product_attribute_6[#All],2,FALSE),"") -> 14776 | Q12: ==IF(product!Q13<>"",product!Q13,"") -> Aero Styles premium series; LB-Kaido Works widebody; Real Riders rubber tyres | R12: ==IF(product!R13<>"",product!R13,"") -> Aero Styles প্রিমিয়াম সিরিজ; LB-Kaido Works ওয়াইডবডি; Real Riders রাবার টায়ার | S12: ==IF(product!S13<>"",product!S13,"") -> LB-Kaido Works ওয়াইডবডি R32, পরিচ্ছন্ন সাদা রেস ট্রিমে — একদম নতুন Aero Styles সিরিজের হিরো কার। মেটাল বডি ও মেটাল বেস, Real Riders রাবার টায়ার। স্কেল: 1:64 · প্রস্তুতকারক: Mattel · সিরিজ: Car Culture — Aero Styles · মডেল নম্বর: FPY86 গঠন: Diecast metal body, metal base, Real Riders rubber tyres প্যাকেজিং: অরিজিনাল Hot Wheels প্রিমিয়াম ব্লিস্টার কার্ডে সিলড প্রস্তুতকারকের বয়সসীমা: ৩ বছর ও তদূর্ধ্ব (Mattel অফিসিয়াল)। ১০০% আসল — DiecastBD কর্তৃক আমদানিকৃত ও হাতে যাচাইকৃত। | T12: ==IF(product!T13<>"",product!T13,"") -> LB-Kaido Works widebody R32 in clean white race trim — the hero car of the brand-new Aero Styles series. Metal/metal, Real Riders. Scale: 1:64 · Manufacturer: Mattel · Series: Car Culture — Aero Styles · Model no: FPY86 Construction: Diecast metal body, metal base, Real Riders rubber tyres Packaging: sealed on the original Hot Wheels premium blister card Manufacturer age grade: 3 years and up (Mattel official). 100% authentic — imported and hand-verified by DiecastBD. | U12: ==IF(product!U13<>"",product!U13,"") -> 1 x Hot Wheels Car Culture — LB-Kaido Works Nissan Skyline GT-R R32 (Aero Styles), sealed on the original Hot Wheels premium blister card | V12: ==IF(product!V13<>"",product!V13,"") -> No manufacturer or seller warranty is offered on collectible diecast models. Every piece is supplied factory-sealed in its original packaging, is 100% authentic, and is hand-inspected before dispatch. Report any transit damage with the unopened parcel on delivery. | W12: ==IF(product!W13<>"",product!W13,"") -> কালেক্টিবল ডাইকাস্ট মডেলের ক্ষেত্রে কোনো ম্যানুফ্যাকচারার বা সেলার ওয়ারেন্টি দেওয়া হয় না। প্রতিটি পিস অরিজিনাল প্যাকেজিংয়ে ফ্যাক্টরি-সিলড অবস্থায় সরবরাহ করা হয়, ১০০% আসল, এবং পাঠানোর আগে হাতে যাচাই করা হয়। ডেলিভারির সময় পার্সেল না খুলে ট্রানজিটে কোনো ক্ষতি হয়ে থাকলে সঙ্গে সঙ্গে জানান। | X12: ==IF('product'!X13<>"", VLOOKUP('product'!X13,product_attribute_100[#All],2,FALSE),"") -> 3 | Y12: ==IF('product'!Y13<>"", VLOOKUP('product'!Y13,product_attribute_101[#All],2,FALSE),"") | Z12: ==IF(product!Z13<>"",product!Z13,"") -> 0.2 | AA12: ==IF(product!AA13<>"",product!AA13,"") -> 18 | AB12: ==IF(product!AB13<>"",product!AB13,"") -> 15 | AC12: ==IF(product!AC13<>"",product!AC13,"") -> 6 | AD12: ==IF('product'!AD13<>"", VLOOKUP('product'!AD13,product_attribute_14[#All],2,FALSE),"") -> 560 | AE12: ==IF(product!AE13<>"",product!AE13,"") -> DCBD-HWCC-009 | AF12: ==IF(product!AF13<>"",product!AF13,"") -> DCBD-HWCC-009 | AG12: ==IF(product!AG13<>"",product!AG13,"") -> https://cdn.cartup.com/product/375e5a3e-b231-4b51-97b0-619fba461cc6.webp | AH12: ==IF(product!AH13<>"",product!AH13,"") -> 3 | AI12: ==IF(product!AI13<>"",product!AI13,"") -> 2390 | AJ12: ==IF(product!AJ13<>"",product!AJ13,"") -> 2230 | AK12: ==IF(product!AK13<>"",product!AK13,"") -> 46231 | AL12: ==IF(product!AL13<>"",product!AL13,"") -> 46596.999 | AM12: ==IF(product!AM13<>"",product!AM13,"")
A13: ==IF(product!A14<>"",product!A14,"") -> Hot Wheels Car Culture — 2008 Audi A4 DTM Touring Car (Aero Styles) | B13: ==IF(product!B14<>"",product!B14,"") -> Hot Wheels Car Culture — 2008 Audi A4 DTM ১:৬৪ ডাইকাস্ট মডেল কার (Aero Styles) | C13: ==IF(product!C14<>"",product!C14,"") -> https://cdn.cartup.com/product/1580fb8a-5afd-4058-ac12-2604ff981728.webp | D13: ==IF(product!D14<>"",product!D14,"") | E13: ==IF(product!E14<>"",product!E14,"") | F13: ==IF(product!F14<>"",product!F14,"") | G13: ==IF(product!G14<>"",product!G14,"") | H13: ==IF(product!H14<>"",product!H14,"") | ... K13: ==IF(product!K14<>"",product!K14,"") | L13: ==IF('product'!L14<>"", VLOOKUP('product'!L14,product_attribute_1[#All],2,FALSE),"") -> 519 | M13: ==IF('product'!M14<>"", VLOOKUP('product'!M14,product_attribute_2[#All],2,FALSE),"") -> 2 | N13: ==IF(product!N14<>"",product!N14,"") -> car culture, audi, a4, dtm, aero styles, motorsport | O13: ==IF('product'!O14<>"", VLOOKUP('product'!O14,product_attribute_7[#All],2,FALSE),"") -> 392 | P13: ==IF('product'!P14<>"", VLOOKUP('product'!P14,product_attribute_6[#All],2,FALSE),"") -> 14776 | Q13: ==IF(product!Q14<>"",product!Q14,"") -> Aero Styles premium series; Metal body & metal base; Real Riders rubber tyres | R13: ==IF(product!R14<>"",product!R14,"") -> Aero Styles প্রিমিয়াম সিরিজ; মেটাল বডি ও মেটাল বেস; Real Riders রাবার টায়ার | S13: ==IF(product!S14<>"",product!S14,"") -> ২০০৮ সালের Audi A4 DTM টুরিং কার, গাঢ় কালো রঙে — প্রিমিয়াম Aero Styles কার্ডে মোটরস্পোর্টের ঐতিহ্য। স্কেল: 1:64 · প্রস্তুতকারক: Mattel · সিরিজ: Car Culture — Aero Styles · মডেল নম্বর: FPY86 গঠন: Diecast metal body, metal base, Real Riders rubber tyres প্যাকেজিং: অরিজিনাল Hot Wheels প্রিমিয়াম ব্লিস্টার কার্ডে সিলড প্রস্তুতকারকের বয়সসীমা: ৩ বছর ও তদূর্ধ্ব (Mattel অফিসিয়াল)। ১০০% আসল — DiecastBD কর্তৃক আমদানিকৃত ও হাতে যাচাইকৃত। | T13: ==IF(product!T14<>"",product!T14,"") -> 2008 Audi A4 DTM touring car in menacing black — motorsport pedigree on a premium Aero Styles card. Scale: 1:64 · Manufacturer: Mattel · Series: Car Culture — Aero Styles · Model no: FPY86 Construction: Diecast metal body, metal base, Real Riders rubber tyres Packaging: sealed on the original Hot Wheels premium blister card Manufacturer age grade: 3 years and up (Mattel official). 100% authentic — imported and hand-verified by DiecastBD. | U13: ==IF(product!U14<>"",product!U14,"") -> 1 x Hot Wheels Car Culture — 2008 Audi A4 DTM Touring Car (Aero Styles), sealed on the original Hot Wheels premium blister card | V13: ==IF(product!V14<>"",product!V14,"") -> No manufacturer or seller warranty is offered on collectible diecast models. Every piece is supplied factory-sealed in its original packaging, is 100% authentic, and is hand-inspected before dispatch. Report any transit damage with the unopened parcel on delivery. | W13: ==IF(product!W14<>"",product!W14,"") -> কালেক্টিবল ডাইকাস্ট মডেলের ক্ষেত্রে কোনো ম্যানুফ্যাকচারার বা সেলার ওয়ারেন্টি দেওয়া হয় না। প্রতিটি পিস অরিজিনাল প্যাকেজিংয়ে ফ্যাক্টরি-সিলড অবস্থায় সরবরাহ করা হয়, ১০০% আসল, এবং পাঠানোর আগে হাতে যাচাই করা হয়। ডেলিভারির সময় পার্সেল না খুলে ট্রানজিটে কোনো ক্ষতি হয়ে থাকলে সঙ্গে সঙ্গে জানান। | X13: ==IF('product'!X14<>"", VLOOKUP('product'!X14,product_attribute_100[#All],2,FALSE),"") -> 3 | Y13: ==IF('product'!Y14<>"", VLOOKUP('product'!Y14,product_attribute_101[#All],2,FALSE),"") | Z13: ==IF(product!Z14<>"",product!Z14,"") -> 0.2 | AA13: ==IF(product!AA14<>"",product!AA14,"") -> 18 | AB13: ==IF(product!AB14<>"",product!AB14,"") -> 15 | AC13: ==IF(product!AC14<>"",product!AC14,"") -> 6 | AD13: ==IF('product'!AD14<>"", VLOOKUP('product'!AD14,product_attribute_14[#All],2,FALSE),"") -> 575 | AE13: ==IF(product!AE14<>"",product!AE14,"") -> DCBD-HWCC-010 | AF13: ==IF(product!AF14<>"",product!AF14,"") -> DCBD-HWCC-010 | AG13: ==IF(product!AG14<>"",product!AG14,"") -> https://cdn.cartup.com/product/1580fb8a-5afd-4058-ac12-2604ff981728.webp | AH13: ==IF(product!AH14<>"",product!AH14,"") -> 1 | AI13: ==IF(product!AI14<>"",product!AI14,"") -> 2100 | AJ13: ==IF(product!AJ14<>"",product!AJ14,"") -> 1960 | AK13: ==IF(product!AK14<>"",product!AK14,"") -> 46231 | AL13: ==IF(product!AL14<>"",product!AL14,"") -> 46596.999 | AM13: ==IF(product!AM14<>"",product!AM14,"")
... A501: ==IF(product!A502<>"",product!A502,"") | B501: ==IF(product!B502<>"",product!B502,"") | C501: ==IF(product!C502<>"",product!C502,"") | D501: ==IF(product!D502<>"",product!D502,"") | E501: ==IF(product!E502<>"",product!E502,"") | F501: ==IF(product!F502<>"",product!F502,"") | G501: ==IF(product!G502<>"",product!G502,"") | H501: ==IF(product!H502<>"",product!H502,"") | ... K501: ==IF(product!K502<>"",product!K502,"") | L501: ==IF('product'!L502<>"", VLOOKUP('product'!L502,product_attribute_1[#All],2,FALSE),"") | M501: ==IF('product'!M502<>"", VLOOKUP('product'!M502,product_attribute_2[#All],2,FALSE),"") | N501: ==IF(product!N502<>"",product!N502,"") | O501: ==IF('product'!O502<>"", VLOOKUP('product'!O502,product_attribute_7[#All],2,FALSE),"") | P501: ==IF('product'!P502<>"", VLOOKUP('product'!P502,product_attribute_6[#All],2,FALSE),"") | Q501: ==IF(product!Q502<>"",product!Q502,"") | R501: ==IF(product!R502<>"",product!R502,"") | S501: ==IF(product!S502<>"",product!S502,"") | T501: ==IF(product!T502<>"",product!T502,"") | U501: ==IF(product!U502<>"",product!U502,"") | V501: ==IF(product!V502<>"",product!V502,"") | W501: ==IF(product!W502<>"",product!W502,"") | X501: ==IF('product'!X502<>"", VLOOKUP('product'!X502,product_attribute_100[#All],2,FALSE),"") | Y501: ==IF('product'!Y502<>"", VLOOKUP('product'!Y502,product_attribute_101[#All],2,FALSE),"") | Z501: ==IF(product!Z502<>"",product!Z502,"") | AA501: ==IF(product!AA502<>"",product!AA502,"") | AB501: ==IF(product!AB502<>"",product!AB502,"") | AC501: ==IF(product!AC502<>"",product!AC502,"") | AD501: ==IF('product'!AD502<>"", VLOOKUP('product'!AD502,product_attribute_14[#All],2,FALSE),"") | AE501: ==IF(product!AE502<>"",product!AE502,"") | AF501: ==IF(product!AF502<>"",product!AF502,"") | AG501: ==IF(product!AG502<>"",product!AG502,"") | AH501: ==IF(product!AH502<>"",product!AH502,"") | AI501: ==IF(product!AI502<>"",product!AI502,"") | AJ501: ==IF(product!AJ502<>"",product!AJ502,"") | AK501: ==IF(product!AK502<>"",product!AK502,"") | AL501: ==IF(product!AL502<>"",product!AL502,"") | AM501: ==IF(product!AM502<>"",product!AM502,"")

Sheet policy
A1: Policy Document
A3: This document outlines the policies for uploading and managing our Excel spreadsheets.
A5: Mandatory Fields
A6: Fields Marked with (*): These fields are mandatory, and valid data must be entered.
A8: Images
A9: Product Images: At least one product image link and one variant image link must be provided.
A10: ImageKey Usage: Please input the ImageKey of the downloaded Excel batch into the fields: Product Image 1(*), Product Image 2, Product Image 3, Product Image 4, Product Image 5, Product Image 6, Product Image 7, and Product Image 8.
A12: Product Variants
A13: Duplicate Variants: For the same product, variant combinations cannot be duplicated.
A15: Unique Identifiers
A16: Seller SKU: The Seller SKU must be unique across the entire system.
A17: Parent SKU: If multiple products share the same Parent SKU, they will be uploaded as multiple variants of a single product.
... A25: Dropdown Values: Only valid data can be entered in dropdown fields; the dropdown values must be used as provided.
